[{"theater_type":"MEGABOX","theater_name":"강남","city":"서울","movie_title":"슈퍼 마리오 브라더스","start_time":"15:00","district":"서초구"},{"theater_type":"MEGABOX","theater_name":"강남","city":"서울","movie_title":"슈퍼 마리오 브라더스","start_time":"17:00","district":"서초구"},{"theater_type":"MEGABOX","theater_name":"강남","city":"서울","movie_title":"슈퍼 마리오 브라더스","start_time":"19:00","district":"서초구"},{"theater_type":"MEGABOX","theater_name":"강남","city":"서울","movie_title":"슈퍼 마리오 브라더스","start_time":"13:00","district":"서초구"},{"theater_type":"MEGABOX","theater_name":"강남","city":"서울","movie_title":"슈퍼 마리오 브라더스","start_time":"10:00","district":"서초구"},{"theater_type":"MEGABOX","theater_name":"강남","city":"서울","movie_title":"슈퍼 마리오 브라더스","start_time":"12:00","district":"서초구"},{"theater_type":"MEGABOX","theater_name":"강남","city":"서울","movie_title":"슈퍼 마리오 브라더스","start_time":"14:00","district":"서초구"},{"theater_type":"MEGABOX","theater_name":"강남","city":"서울","movie_title":"슈퍼 마리오 브라더스","start_time":"16:00","district":"서초구"},{"theater_type":"MEGABOX","theater_name":"강남","city":"서울","movie_title":"슈퍼 마리오 브라더스","start_time":"18:00","district":"서초구"},{"theater_type":"MEGABOX","theater_name":"강남","city":"서울","movie_title":"슈퍼 마리오 브라더스","start_time":"20:00","district":"서초구"},{"theater_type":"MEGABOX","theater_name":"강남","city":"서울","movie_title":"슈퍼 마리오 브라더스","start_time":"22:00","district":"서초구"},{"theater_type":"MEGABOX","theater_name":"강남","city":"서울","movie_title":"드림","start_time":"9:50","district":"서초구"},{"theater_type":"MEGABOX","theater_name":"강남","city":"서울","movie_title":"드림","start_time":"12:20","district":"서초구"},{"theater_type":"MEGABOX","theater_name":"강남","city":"서울","movie_title":"드림","start_time":"14:50","district":"서초구"},{"theater_type":"MEGABOX","theater_name":"강남","city":"서울","movie_title":"드림","start_time":"17:20","district":"서초구"},{"theater_type":"MEGABOX","theater_name":"강남","city":"서울","movie_title":"드림","start_time":"19:50","district":"서초구"},{"theater_type":"MEGABOX","theater_name":"강남","city":"서울","movie_title":"드림","start_time":"10:50","district":"서초구"},{"theater_type":"MEGABOX","theater_name":"강남","city":"서울","movie_title":"드림","start_time":"13:20","district":"서초구"},{"theater_type":"MEGABOX","theater_name":"강남","city":"서울","movie_title":"드림","start_time":"15:50","district":"서초구"},{"theater_type":"MEGABOX","theater_name":"강남","city":"서울","movie_title":"드림","start_time":"18:20","district":"서초구"},{"theater_type":"MEGABOX","theater_name":"강남","city":"서울","movie_title":"드림","start_time":"20:50","district":"서초구"},{"theater_type":"MEGABOX","theater_name":"강남","city":"서울","movie_title":"드림","start_time":"16:30","district":"서초구"},{"theater_type":"MEGABOX","theater_name":"강남","city":"서울","movie_title":"드림","start_time":"19:00","district":"서초구"},{"theater_type":"MEGABOX","theater_name":"강남","city":"서울","movie_title":"드림","start_time":"21:40","district":"서초구"},{"theater_type":"MEGABOX","theater_name":"강남","city":"서울","movie_title":"더 퍼스트 슬램덩크","start_time":"12:25","district":"서초구"},{"theater_type":"MEGABOX","theater_name":"강남","city":"서울","movie_title":"스즈메의 문단속","start_time":"10:30","district":"서초구"},{"theater_type":"MEGABOX","theater_name":"강남","city":"서울","movie_title":"스즈메의 문단속","start_time":"15:00","district":"서초구"},{"theater_type":"MEGABOX","theater_name":"강남","city":"서울","movie_title":"스즈메의 문단속","start_time":"17:30","district":"서초구"},{"theater_type":"MEGABOX","theater_name":"강남","city":"서울","movie_title":"스즈메의 문단속","start_time":"20:00","district":"서초구"},{"theater_type":"MEGABOX","theater_name":"강남","city":"서울","movie_title":"존 윅 4","start_time":"21:00","district":"서초구"},{"theater_type":"MEGABOX","theater_name":"강남","city":"서울","movie_title":"존 윅 4","start_time":"12:45","district":"서초구"},{"theater_type":"MEGABOX","theater_name":"강남","city":"서울","movie_title":"존 윅 4","start_time":"16:00","district":"서초구"},{"theater_type":"MEGABOX","theater_name":"강남","city":"서울","movie_title":"존 윅 4","start_time":"19:20","district":"서초구"},{"theater_type":"MEGABOX","theater_name":"강남","city":"서울","movie_title":"리바운드","start_time":"11:30","district":"서초구"},{"theater_type":"MEGABOX","theater_name":"강남","city":"서울","movie_title":"리바운드","start_time":"14:00","district":"서초구"},{"theater_type":"MEGABOX","theater_name":"강남대로(씨티)","city":"서울","movie_title":"슈퍼 마리오 브라더스","start_time":"13:30","district":"강남구"},{"theater_type":"MEGABOX","theater_name":"강남대로(씨티)","city":"서울","movie_title":"슈퍼 마리오 브라더스","start_time":"15:30","district":"강남구"},{"theater_type":"MEGABOX","theater_name":"강남대로(씨티)","city":"서울","movie_title":"슈퍼 마리오 브라더스","start_time":"17:30","district":"강남구"},{"theater_type":"MEGABOX","theater_name":"강남대로(씨티)","city":"서울","movie_title":"슈퍼 마리오 브라더스","start_time":"19:30","district":"강남구"},{"theater_type":"MEGABOX","theater_name":"강남대로(씨티)","city":"서울","movie_title":"슈퍼 마리오 브라더스","start_time":"21:30","district":"강남구"},{"theater_type":"MEGABOX","theater_name":"강남대로(씨티)","city":"서울","movie_title":"슈퍼 마리오 브라더스","start_time":"10:00","district":"강남구"},{"theater_type":"MEGABOX","theater_name":"강남대로(씨티)","city":"서울","movie_title":"슈퍼 마리오 브라더스","start_time":"12:00","district":"강남구"},{"theater_type":"MEGABOX","theater_name":"강남대로(씨티)","city":"서울","movie_title":"드림","start_time":"11:30","district":"강남구"},{"theater_type":"MEGABOX","theater_name":"강남대로(씨티)","city":"서울","movie_title":"드림","start_time":"14:00","district":"강남구"},{"theater_type":"MEGABOX","theater_name":"강남대로(씨티)","city":"서울","movie_title":"드림","start_time":"16:30","district":"강남구"},{"theater_type":"MEGABOX","theater_name":"강남대로(씨티)","city":"서울","movie_title":"드림","start_time":"19:00","district":"강남구"},{"theater_type":"MEGABOX","theater_name":"강남대로(씨티)","city":"서울","movie_title":"드림","start_time":"21:30","district":"강남구"},{"theater_type":"MEGABOX","theater_name":"강남대로(씨티)","city":"서울","movie_title":"더 퍼스트 슬램덩크","start_time":"16:30","district":"강남구"},{"theater_type":"MEGABOX","theater_name":"강남대로(씨티)","city":"서울","movie_title":"스즈메의 문단속","start_time":"11:00","district":"강남구"},{"theater_type":"MEGABOX","theater_name":"강남대로(씨티)","city":"서울","movie_title":"스즈메의 문단속","start_time":"14:00","district":"강남구"},{"theater_type":"MEGABOX","theater_name":"강남대로(씨티)","city":"서울","movie_title":"스즈메의 문단속","start_time":"19:00","district":"강남구"},{"theater_type":"MEGABOX","theater_name":"강남대로(씨티)","city":"서울","movie_title":"스즈메의 문단속","start_time":"21:30","district":"강남구"},{"theater_type":"MEGABOX","theater_name":"강남대로(씨티)","city":"서울","movie_title":"존 윅 4","start_time":"10:35","district":"강남구"},{"theater_type":"MEGABOX","theater_name":"강남대로(씨티)","city":"서울","movie_title":"존 윅 4","start_time":"13:50","district":"강남구"},{"theater_type":"MEGABOX","theater_name":"강남대로(씨티)","city":"서울","movie_title":"존 윅 4","start_time":"17:05","district":"강남구"},{"theater_type":"MEGABOX","theater_name":"강남대로(씨티)","city":"서울","movie_title":"존 윅 4","start_time":"20:20","district":"강남구"},{"theater_type":"MEGABOX","theater_name":"강동","city":"서울","movie_title":"슈퍼 마리오 브라더스","start_time":"15:20","district":"강동구"},{"theater_type":"MEGABOX","theater_name":"강동","city":"서울","movie_title":"슈퍼 마리오 브라더스","start_time":"19:20","district":"강동구"},{"theater_type":"MEGABOX","theater_name":"강동","city":"서울","movie_title":"슈퍼 마리오 브라더스","start_time":"9:20","district":"강동구"},{"theater_type":"MEGABOX","theater_name":"강동","city":"서울","movie_title":"슈퍼 마리오 브라더스","start_time":"11:20","district":"강동구"},{"theater_type":"MEGABOX","theater_name":"강동","city":"서울","movie_title":"슈퍼 마리오 브라더스","start_time":"17:20","district":"강동구"},{"theater_type":"MEGABOX","theater_name":"강동","city":"서울","movie_title":"슈퍼 마리오 브라더스","start_time":"21:20","district":"강동구"},{"theater_type":"MEGABOX","theater_name":"강동","city":"서울","movie_title":"슈퍼 마리오 브라더스","start_time":"13:20","district":"강동구"},{"theater_type":"MEGABOX","theater_name":"강동","city":"서울","movie_title":"슈퍼 마리오 브라더스","start_time":"10:25","district":"강동구"},{"theater_type":"MEGABOX","theater_name":"강동","city":"서울","movie_title":"슈퍼 마리오 브라더스","start_time":"12:25","district":"강동구"},{"theater_type":"MEGABOX","theater_name":"강동","city":"서울","movie_title":"슈퍼 마리오 브라더스","start_time":"18:20","district":"강동구"},{"theater_type":"MEGABOX","theater_name":"강동","city":"서울","movie_title":"슈퍼 마리오 브라더스","start_time":"14:20","district":"강동구"},{"theater_type":"MEGABOX","theater_name":"강동","city":"서울","movie_title":"드림","start_time":"10:40","district":"강동구"},{"theater_type":"MEGABOX","theater_name":"강동","city":"서울","movie_title":"드림","start_time":"13:15","district":"강동구"},{"theater_type":"MEGABOX","theater_name":"강동","city":"서울","movie_title":"드림","start_time":"15:50","district":"강동구"},{"theater_type":"MEGABOX","theater_name":"강동","city":"서울","movie_title":"드림","start_time":"18:25","district":"강동구"},{"theater_type":"MEGABOX","theater_name":"강동","city":"서울","movie_title":"드림","start_time":"21:00","district":"강동구"},{"theater_type":"MEGABOX","theater_name":"강동","city":"서울","movie_title":"드림","start_time":"9:40","district":"강동구"},{"theater_type":"MEGABOX","theater_name":"강동","city":"서울","movie_title":"드림","start_time":"12:15","district":"강동구"},{"theater_type":"MEGABOX","theater_name":"강동","city":"서울","movie_title":"드림","start_time":"14:50","district":"강동구"},{"theater_type":"MEGABOX","theater_name":"강동","city":"서울","movie_title":"드림","start_time":"17:25","district":"강동구"},{"theater_type":"MEGABOX","theater_name":"강동","city":"서울","movie_title":"드림","start_time":"20:00","district":"강동구"},{"theater_type":"MEGABOX","theater_name":"강동","city":"서울","movie_title":"더 퍼스트 슬램덩크","start_time":"15:35","district":"강동구"},{"theater_type":"MEGABOX","theater_name":"강동","city":"서울","movie_title":"더 퍼스트 슬램덩크","start_time":"20:50","district":"강동구"},{"theater_type":"MEGABOX","theater_name":"강동","city":"서울","movie_title":"더 퍼스트 슬램덩크","start_time":"18:25","district":"강동구"},{"theater_type":"MEGABOX","theater_name":"강동","city":"서울","movie_title":"스즈메의 문단속","start_time":"14:25","district":"강동구"},{"theater_type":"MEGABOX","theater_name":"강동","city":"서울","movie_title":"스즈메의 문단속","start_time":"13:00","district":"강동구"},{"theater_type":"MEGABOX","theater_name":"강동","city":"서울","movie_title":"스즈메의 문단속","start_time":"18:15","district":"강동구"},{"theater_type":"MEGABOX","theater_name":"강동","city":"서울","movie_title":"스즈메의 문단속","start_time":"9:45","district":"강동구"},{"theater_type":"MEGABOX","theater_name":"강동","city":"서울","movie_title":"스즈메의 문단속","start_time":"21:00","district":"강동구"},{"theater_type":"MEGABOX","theater_name":"강동","city":"서울","movie_title":"존 윅 4","start_time":"16:55","district":"강동구"},{"theater_type":"MEGABOX","theater_name":"강동","city":"서울","movie_title":"존 윅 4","start_time":"20:10","district":"강동구"},{"theater_type":"MEGABOX","theater_name":"강동","city":"서울","movie_title":"존 윅 4","start_time":"11:00","district":"강동구"},{"theater_type":"MEGABOX","theater_name":"강동","city":"서울","movie_title":"존 윅 4","start_time":"14:45","district":"강동구"},{"theater_type":"MEGABOX","theater_name":"강동","city":"서울","movie_title":"리바운드","start_time":"9:35","district":"강동구"},{"theater_type":"MEGABOX","theater_name":"강동","city":"서울","movie_title":"리바운드","start_time":"21:00","district":"강동구"},{"theater_type":"MEGABOX","theater_name":"강동","city":"서울","movie_title":"리바운드","start_time":"15:55","district":"강동구"},{"theater_type":"MEGABOX","theater_name":"군자","city":"서울","movie_title":"슈퍼 마리오 브라더스","start_time":"9:20","district":"광진구"},{"theater_type":"MEGABOX","theater_name":"군자","city":"서울","movie_title":"슈퍼 마리오 브라더스","start_time":"11:20","district":"광진구"},{"theater_type":"MEGABOX","theater_name":"군자","city":"서울","movie_title":"슈퍼 마리오 브라더스","start_time":"13:20","district":"광진구"},{"theater_type":"MEGABOX","theater_name":"군자","city":"서울","movie_title":"슈퍼 마리오 브라더스","start_time":"15:20","district":"광진구"},{"theater_type":"MEGABOX","theater_name":"군자","city":"서울","movie_title":"슈퍼 마리오 브라더스","start_time":"17:20","district":"광진구"},{"theater_type":"MEGABOX","theater_name":"군자","city":"서울","movie_title":"슈퍼 마리오 브라더스","start_time":"19:20","district":"광진구"},{"theater_type":"MEGABOX","theater_name":"군자","city":"서울","movie_title":"슈퍼 마리오 브라더스","start_time":"21:20","district":"광진구"},{"theater_type":"MEGABOX","theater_name":"군자","city":"서울","movie_title":"슈퍼 마리오 브라더스","start_time":"10:20","district":"광진구"},{"theater_type":"MEGABOX","theater_name":"군자","city":"서울","movie_title":"슈퍼 마리오 브라더스","start_time":"12:20","district":"광진구"},{"theater_type":"MEGABOX","theater_name":"군자","city":"서울","movie_title":"슈퍼 마리오 브라더스","start_time":"14:20","district":"광진구"},{"theater_type":"MEGABOX","theater_name":"군자","city":"서울","movie_title":"드림","start_time":"11:00","district":"광진구"},{"theater_type":"MEGABOX","theater_name":"군자","city":"서울","movie_title":"드림","start_time":"13:30","district":"광진구"},{"theater_type":"MEGABOX","theater_name":"군자","city":"서울","movie_title":"드림","start_time":"16:00","district":"광진구"},{"theater_type":"MEGABOX","theater_name":"군자","city":"서울","movie_title":"드림","start_time":"18:30","district":"광진구"},{"theater_type":"MEGABOX","theater_name":"군자","city":"서울","movie_title":"드림","start_time":"21:00","district":"광진구"},{"theater_type":"MEGABOX","theater_name":"군자","city":"서울","movie_title":"드림","start_time":"9:45","district":"광진구"},{"theater_type":"MEGABOX","theater_name":"군자","city":"서울","movie_title":"드림","start_time":"12:15","district":"광진구"},{"theater_type":"MEGABOX","theater_name":"군자","city":"서울","movie_title":"드림","start_time":"14:45","district":"광진구"},{"theater_type":"MEGABOX","theater_name":"군자","city":"서울","movie_title":"드림","start_time":"17:15","district":"광진구"},{"theater_type":"MEGABOX","theater_name":"군자","city":"서울","movie_title":"드림","start_time":"19:45","district":"광진구"},{"theater_type":"MEGABOX","theater_name":"군자","city":"서울","movie_title":"더 퍼스트 슬램덩크","start_time":"9:10","district":"광진구"},{"theater_type":"MEGABOX","theater_name":"군자","city":"서울","movie_title":"더 퍼스트 슬램덩크","start_time":"16:10","district":"광진구"},{"theater_type":"MEGABOX","theater_name":"군자","city":"서울","movie_title":"스즈메의 문단속","start_time":"16:05","district":"광진구"},{"theater_type":"MEGABOX","theater_name":"군자","city":"서울","movie_title":"스즈메의 문단속","start_time":"20:50","district":"광진구"},{"theater_type":"MEGABOX","theater_name":"군자","city":"서울","movie_title":"스즈메의 문단속","start_time":"13:40","district":"광진구"},{"theater_type":"MEGABOX","theater_name":"군자","city":"서울","movie_title":"존 윅 4","start_time":"17:10","district":"광진구"},{"theater_type":"MEGABOX","theater_name":"군자","city":"서울","movie_title":"존 윅 4","start_time":"20:25","district":"광진구"},{"theater_type":"MEGABOX","theater_name":"군자","city":"서울","movie_title":"존 윅 4","start_time":"9:35","district":"광진구"},{"theater_type":"MEGABOX","theater_name":"군자","city":"서울","movie_title":"존 윅 4","start_time":"12:50","district":"광진구"},{"theater_type":"MEGABOX","theater_name":"군자","city":"서울","movie_title":"리바운드","start_time":"20:35","district":"광진구"},{"theater_type":"MEGABOX","theater_name":"더 부티크 목동현대백화점","city":"서울","movie_title":"슈퍼 마리오 브라더스","start_time":"22:30","district":"양천구"},{"theater_type":"MEGABOX","theater_name":"더 부티크 목동현대백화점","city":"서울","movie_title":"슈퍼 마리오 브라더스","start_time":"14:10","district":"양천구"},{"theater_type":"MEGABOX","theater_name":"더 부티크 목동현대백화점","city":"서울","movie_title":"슈퍼 마리오 브라더스","start_time":"16:15","district":"양천구"},{"theater_type":"MEGABOX","theater_name":"더 부티크 목동현대백화점","city":"서울","movie_title":"슈퍼 마리오 브라더스","start_time":"18:20","district":"양천구"},{"theater_type":"MEGABOX","theater_name":"더 부티크 목동현대백화점","city":"서울","movie_title":"슈퍼 마리오 브라더스","start_time":"20:25","district":"양천구"},{"theater_type":"MEGABOX","theater_name":"더 부티크 목동현대백화점","city":"서울","movie_title":"슈퍼 마리오 브라더스","start_time":"10:05","district":"양천구"},{"theater_type":"MEGABOX","theater_name":"더 부티크 목동현대백화점","city":"서울","movie_title":"슈퍼 마리오 브라더스","start_time":"12:05","district":"양천구"},{"theater_type":"MEGABOX","theater_name":"더 부티크 목동현대백화점","city":"서울","movie_title":"슈퍼 마리오 브라더스","start_time":"14:40","district":"양천구"},{"theater_type":"MEGABOX","theater_name":"더 부티크 목동현대백화점","city":"서울","movie_title":"슈퍼 마리오 브라더스","start_time":"16:45","district":"양천구"},{"theater_type":"MEGABOX","theater_name":"더 부티크 목동현대백화점","city":"서울","movie_title":"슈퍼 마리오 브라더스","start_time":"18:50","district":"양천구"},{"theater_type":"MEGABOX","theater_name":"더 부티크 목동현대백화점","city":"서울","movie_title":"슈퍼 마리오 브라더스","start_time":"20:55","district":"양천구"},{"theater_type":"MEGABOX","theater_name":"더 부티크 목동현대백화점","city":"서울","movie_title":"슈퍼 마리오 브라더스","start_time":"23:00","district":"양천구"},{"theater_type":"MEGABOX","theater_name":"더 부티크 목동현대백화점","city":"서울","movie_title":"슈퍼 마리오 브라더스","start_time":"10:30","district":"양천구"},{"theater_type":"MEGABOX","theater_name":"더 부티크 목동현대백화점","city":"서울","movie_title":"슈퍼 마리오 브라더스","start_time":"12:35","district":"양천구"},{"theater_type":"MEGABOX","theater_name":"더 부티크 목동현대백화점","city":"서울","movie_title":"슈퍼 마리오 브라더스","start_time":"13:25","district":"양천구"},{"theater_type":"MEGABOX","theater_name":"더 부티크 목동현대백화점","city":"서울","movie_title":"슈퍼 마리오 브라더스","start_time":"21:45","district":"양천구"},{"theater_type":"MEGABOX","theater_name":"더 부티크 목동현대백화점","city":"서울","movie_title":"슈퍼 마리오 브라더스","start_time":"11:20","district":"양천구"},{"theater_type":"MEGABOX","theater_name":"더 부티크 목동현대백화점","city":"서울","movie_title":"슈퍼 마리오 브라더스","start_time":"15:30","district":"양천구"},{"theater_type":"MEGABOX","theater_name":"더 부티크 목동현대백화점","city":"서울","movie_title":"슈퍼 마리오 브라더스","start_time":"17:35","district":"양천구"},{"theater_type":"MEGABOX","theater_name":"더 부티크 목동현대백화점","city":"서울","movie_title":"슈퍼 마리오 브라더스","start_time":"19:40","district":"양천구"},{"theater_type":"MEGABOX","theater_name":"더 부티크 목동현대백화점","city":"서울","movie_title":"드림","start_time":"9:40","district":"양천구"},{"theater_type":"MEGABOX","theater_name":"더 부티크 목동현대백화점","city":"서울","movie_title":"드림","start_time":"12:15","district":"양천구"},{"theater_type":"MEGABOX","theater_name":"더 부티크 목동현대백화점","city":"서울","movie_title":"드림","start_time":"14:50","district":"양천구"},{"theater_type":"MEGABOX","theater_name":"더 부티크 목동현대백화점","city":"서울","movie_title":"드림","start_time":"17:25","district":"양천구"},{"theater_type":"MEGABOX","theater_name":"더 부티크 목동현대백화점","city":"서울","movie_title":"드림","start_time":"20:00","district":"양천구"},{"theater_type":"MEGABOX","theater_name":"더 부티크 목동현대백화점","city":"서울","movie_title":"드림","start_time":"22:35","district":"양천구"},{"theater_type":"MEGABOX","theater_name":"더 부티크 목동현대백화점","city":"서울","movie_title":"드림","start_time":"18:20","district":"양천구"},{"theater_type":"MEGABOX","theater_name":"더 부티크 목동현대백화점","city":"서울","movie_title":"드림","start_time":"20:55","district":"양천구"},{"theater_type":"MEGABOX","theater_name":"더 부티크 목동현대백화점","city":"서울","movie_title":"드림","start_time":"11:15","district":"양천구"},{"theater_type":"MEGABOX","theater_name":"더 부티크 목동현대백화점","city":"서울","movie_title":"드림","start_time":"13:50","district":"양천구"},{"theater_type":"MEGABOX","theater_name":"더 부티크 목동현대백화점","city":"서울","movie_title":"드림","start_time":"16:25","district":"양천구"},{"theater_type":"MEGABOX","theater_name":"더 부티크 목동현대백화점","city":"서울","movie_title":"드림","start_time":"19:00","district":"양천구"},{"theater_type":"MEGABOX","theater_name":"더 부티크 목동현대백화점","city":"서울","movie_title":"드림","start_time":"21:35","district":"양천구"},{"theater_type":"MEGABOX","theater_name":"더 부티크 목동현대백화점","city":"서울","movie_title":"드림","start_time":"10:10","district":"양천구"},{"theater_type":"MEGABOX","theater_name":"더 부티크 목동현대백화점","city":"서울","movie_title":"드림","start_time":"12:45","district":"양천구"},{"theater_type":"MEGABOX","theater_name":"더 부티크 목동현대백화점","city":"서울","movie_title":"드림","start_time":"15:20","district":"양천구"},{"theater_type":"MEGABOX","theater_name":"더 부티크 목동현대백화점","city":"서울","movie_title":"드림","start_time":"17:55","district":"양천구"},{"theater_type":"MEGABOX","theater_name":"더 부티크 목동현대백화점","city":"서울","movie_title":"드림","start_time":"20:30","district":"양천구"},{"theater_type":"MEGABOX","theater_name":"더 부티크 목동현대백화점","city":"서울","movie_title":"드림","start_time":"23:05","district":"양천구"},{"theater_type":"MEGABOX","theater_name":"더 부티크 목동현대백화점","city":"서울","movie_title":"더 퍼스트 슬램덩크","start_time":"9:40","district":"양천구"},{"theater_type":"MEGABOX","theater_name":"더 부티크 목동현대백화점","city":"서울","movie_title":"스즈메의 문단속","start_time":"12:15","district":"양천구"},{"theater_type":"MEGABOX","theater_name":"더 부티크 목동현대백화점","city":"서울","movie_title":"스즈메의 문단속","start_time":"14:50","district":"양천구"},{"theater_type":"MEGABOX","theater_name":"더 부티크 목동현대백화점","city":"서울","movie_title":"존 윅 4","start_time":"17:25","district":"양천구"},{"theater_type":"MEGABOX","theater_name":"더 부티크 목동현대백화점","city":"서울","movie_title":"존 윅 4","start_time":"20:45","district":"양천구"},{"theater_type":"MEGABOX","theater_name":"더 부티크 목동현대백화점","city":"서울","movie_title":"리바운드","start_time":"15:45","district":"양천구"},{"theater_type":"MEGABOX","theater_name":"동대문","city":"서울","movie_title":"슈퍼 마리오 브라더스","start_time":"9:50","district":"중구"},{"theater_type":"MEGABOX","theater_name":"동대문","city":"서울","movie_title":"슈퍼 마리오 브라더스","start_time":"13:50","district":"중구"},{"theater_type":"MEGABOX","theater_name":"동대문","city":"서울","movie_title":"슈퍼 마리오 브라더스","start_time":"17:50","district":"중구"},{"theater_type":"MEGABOX","theater_name":"동대문","city":"서울","movie_title":"슈퍼 마리오 브라더스","start_time":"19:50","district":"중구"},{"theater_type":"MEGABOX","theater_name":"동대문","city":"서울","movie_title":"슈퍼 마리오 브라더스","start_time":"11:50","district":"중구"},{"theater_type":"MEGABOX","theater_name":"동대문","city":"서울","movie_title":"슈퍼 마리오 브라더스","start_time":"15:50","district":"중구"},{"theater_type":"MEGABOX","theater_name":"동대문","city":"서울","movie_title":"슈퍼 마리오 브라더스","start_time":"10:45","district":"중구"},{"theater_type":"MEGABOX","theater_name":"동대문","city":"서울","movie_title":"슈퍼 마리오 브라더스","start_time":"20:50","district":"중구"},{"theater_type":"MEGABOX","theater_name":"동대문","city":"서울","movie_title":"슈퍼 마리오 브라더스","start_time":"22:50","district":"중구"},{"theater_type":"MEGABOX","theater_name":"동대문","city":"서울","movie_title":"슈퍼 마리오 브라더스","start_time":"14:50","district":"중구"},{"theater_type":"MEGABOX","theater_name":"동대문","city":"서울","movie_title":"슈퍼 마리오 브라더스","start_time":"18:50","district":"중구"},{"theater_type":"MEGABOX","theater_name":"동대문","city":"서울","movie_title":"슈퍼 마리오 브라더스","start_time":"16:50","district":"중구"},{"theater_type":"MEGABOX","theater_name":"동대문","city":"서울","movie_title":"드림","start_time":"10:00","district":"중구"},{"theater_type":"MEGABOX","theater_name":"동대문","city":"서울","movie_title":"드림","start_time":"12:30","district":"중구"},{"theater_type":"MEGABOX","theater_name":"동대문","city":"서울","movie_title":"드림","start_time":"15:00","district":"중구"},{"theater_type":"MEGABOX","theater_name":"동대문","city":"서울","movie_title":"드림","start_time":"17:30","district":"중구"},{"theater_type":"MEGABOX","theater_name":"동대문","city":"서울","movie_title":"드림","start_time":"20:00","district":"중구"},{"theater_type":"MEGABOX","theater_name":"동대문","city":"서울","movie_title":"드림","start_time":"22:30","district":"중구"},{"theater_type":"MEGABOX","theater_name":"동대문","city":"서울","movie_title":"드림","start_time":"10:50","district":"중구"},{"theater_type":"MEGABOX","theater_name":"동대문","city":"서울","movie_title":"드림","start_time":"13:20","district":"중구"},{"theater_type":"MEGABOX","theater_name":"동대문","city":"서울","movie_title":"드림","start_time":"15:50","district":"중구"},{"theater_type":"MEGABOX","theater_name":"동대문","city":"서울","movie_title":"드림","start_time":"18:20","district":"중구"},{"theater_type":"MEGABOX","theater_name":"동대문","city":"서울","movie_title":"드림","start_time":"20:50","district":"중구"},{"theater_type":"MEGABOX","theater_name":"동대문","city":"서울","movie_title":"드림","start_time":"11:40","district":"중구"},{"theater_type":"MEGABOX","theater_name":"동대문","city":"서울","movie_title":"드림","start_time":"14:10","district":"중구"},{"theater_type":"MEGABOX","theater_name":"동대문","city":"서울","movie_title":"드림","start_time":"16:40","district":"중구"},{"theater_type":"MEGABOX","theater_name":"동대문","city":"서울","movie_title":"드림","start_time":"19:10","district":"중구"},{"theater_type":"MEGABOX","theater_name":"동대문","city":"서울","movie_title":"드림","start_time":"21:40","district":"중구"},{"theater_type":"MEGABOX","theater_name":"동대문","city":"서울","movie_title":"더 퍼스트 슬램덩크","start_time":"17:55","district":"중구"},{"theater_type":"MEGABOX","theater_name":"동대문","city":"서울","movie_title":"더 퍼스트 슬램덩크","start_time":"15:25","district":"중구"},{"theater_type":"MEGABOX","theater_name":"동대문","city":"서울","movie_title":"스즈메의 문단속","start_time":"10:25","district":"중구"},{"theater_type":"MEGABOX","theater_name":"동대문","city":"서울","movie_title":"스즈메의 문단속","start_time":"15:20","district":"중구"},{"theater_type":"MEGABOX","theater_name":"동대문","city":"서울","movie_title":"스즈메의 문단속","start_time":"17:50","district":"중구"},{"theater_type":"MEGABOX","theater_name":"동대문","city":"서울","movie_title":"존 윅 4","start_time":"21:50","district":"중구"},{"theater_type":"MEGABOX","theater_name":"동대문","city":"서울","movie_title":"존 윅 4","start_time":"12:10","district":"중구"},{"theater_type":"MEGABOX","theater_name":"동대문","city":"서울","movie_title":"존 윅 4","start_time":"20:25","district":"중구"},{"theater_type":"MEGABOX","theater_name":"동대문","city":"서울","movie_title":"리바운드","start_time":"20:20","district":"중구"},{"theater_type":"MEGABOX","theater_name":"마곡","city":"서울","movie_title":"슈퍼 마리오 브라더스","start_time":"10:00","district":"강서구"},{"theater_type":"MEGABOX","theater_name":"마곡","city":"서울","movie_title":"슈퍼 마리오 브라더스","start_time":"16:00","district":"강서구"},{"theater_type":"MEGABOX","theater_name":"마곡","city":"서울","movie_title":"슈퍼 마리오 브라더스","start_time":"18:00","district":"강서구"},{"theater_type":"MEGABOX","theater_name":"마곡","city":"서울","movie_title":"슈퍼 마리오 브라더스","start_time":"20:00","district":"강서구"},{"theater_type":"MEGABOX","theater_name":"마곡","city":"서울","movie_title":"슈퍼 마리오 브라더스","start_time":"22:00","district":"강서구"},{"theater_type":"MEGABOX","theater_name":"마곡","city":"서울","movie_title":"슈퍼 마리오 브라더스","start_time":"12:00","district":"강서구"},{"theater_type":"MEGABOX","theater_name":"마곡","city":"서울","movie_title":"슈퍼 마리오 브라더스","start_time":"14:00","district":"강서구"},{"theater_type":"MEGABOX","theater_name":"마곡","city":"서울","movie_title":"드림","start_time":"15:50","district":"강서구"},{"theater_type":"MEGABOX","theater_name":"마곡","city":"서울","movie_title":"드림","start_time":"9:50","district":"강서구"},{"theater_type":"MEGABOX","theater_name":"마곡","city":"서울","movie_title":"드림","start_time":"12:25","district":"강서구"},{"theater_type":"MEGABOX","theater_name":"마곡","city":"서울","movie_title":"드림","start_time":"18:20","district":"강서구"},{"theater_type":"MEGABOX","theater_name":"마곡","city":"서울","movie_title":"드림","start_time":"20:55","district":"강서구"},{"theater_type":"MEGABOX","theater_name":"마곡","city":"서울","movie_title":"드림","start_time":"14:25","district":"강서구"},{"theater_type":"MEGABOX","theater_name":"마곡","city":"서울","movie_title":"드림","start_time":"17:00","district":"강서구"},{"theater_type":"MEGABOX","theater_name":"마곡","city":"서울","movie_title":"드림","start_time":"19:35","district":"강서구"},{"theater_type":"MEGABOX","theater_name":"마곡","city":"서울","movie_title":"드림","start_time":"22:10","district":"강서구"},{"theater_type":"MEGABOX","theater_name":"마곡","city":"서울","movie_title":"더 퍼스트 슬램덩크","start_time":"13:15","district":"강서구"},{"theater_type":"MEGABOX","theater_name":"마곡","city":"서울","movie_title":"스즈메의 문단속","start_time":"16:25","district":"강서구"},{"theater_type":"MEGABOX","theater_name":"마곡","city":"서울","movie_title":"스즈메의 문단속","start_time":"10:45","district":"강서구"},{"theater_type":"MEGABOX","theater_name":"마곡","city":"서울","movie_title":"스즈메의 문단속","start_time":"21:50","district":"강서구"},{"theater_type":"MEGABOX","theater_name":"마곡","city":"서울","movie_title":"존 윅 4","start_time":"9:50","district":"강서구"},{"theater_type":"MEGABOX","theater_name":"마곡","city":"서울","movie_title":"존 윅 4","start_time":"13:10","district":"강서구"},{"theater_type":"MEGABOX","theater_name":"마곡","city":"서울","movie_title":"존 윅 4","start_time":"21:10","district":"강서구"},{"theater_type":"MEGABOX","theater_name":"마곡","city":"서울","movie_title":"존 윅 4","start_time":"16:25","district":"강서구"},{"theater_type":"MEGABOX","theater_name":"마곡","city":"서울","movie_title":"존 윅 4","start_time":"19:45","district":"강서구"},{"theater_type":"MEGABOX","theater_name":"마곡","city":"서울","movie_title":"존 윅 4","start_time":"18:30","district":"강서구"},{"theater_type":"MEGABOX","theater_name":"마곡","city":"서울","movie_title":"존 윅 4","start_time":"15:00","district":"강서구"},{"theater_type":"MEGABOX","theater_name":"마곡","city":"서울","movie_title":"존 윅 4","start_time":"11:00","district":"강서구"},{"theater_type":"MEGABOX","theater_name":"마곡","city":"서울","movie_title":"리바운드","start_time":"11:10","district":"강서구"},{"theater_type":"MEGABOX","theater_name":"목동","city":"서울","movie_title":"슈퍼 마리오 브라더스","start_time":"9:30","district":"양천구"},{"theater_type":"MEGABOX","theater_name":"목동","city":"서울","movie_title":"슈퍼 마리오 브라더스","start_time":"11:45","district":"양천구"},{"theater_type":"MEGABOX","theater_name":"목동","city":"서울","movie_title":"슈퍼 마리오 브라더스","start_time":"16:15","district":"양천구"},{"theater_type":"MEGABOX","theater_name":"목동","city":"서울","movie_title":"슈퍼 마리오 브라더스","start_time":"18:30","district":"양천구"},{"theater_type":"MEGABOX","theater_name":"목동","city":"서울","movie_title":"슈퍼 마리오 브라더스","start_time":"20:45","district":"양천구"},{"theater_type":"MEGABOX","theater_name":"목동","city":"서울","movie_title":"슈퍼 마리오 브라더스","start_time":"14:00","district":"양천구"},{"theater_type":"MEGABOX","theater_name":"목동","city":"서울","movie_title":"슈퍼 마리오 브라더스","start_time":"10:30","district":"양천구"},{"theater_type":"MEGABOX","theater_name":"목동","city":"서울","movie_title":"슈퍼 마리오 브라더스","start_time":"12:45","district":"양천구"},{"theater_type":"MEGABOX","theater_name":"목동","city":"서울","movie_title":"슈퍼 마리오 브라더스","start_time":"15:00","district":"양천구"},{"theater_type":"MEGABOX","theater_name":"목동","city":"서울","movie_title":"슈퍼 마리오 브라더스","start_time":"17:20","district":"양천구"},{"theater_type":"MEGABOX","theater_name":"목동","city":"서울","movie_title":"슈퍼 마리오 브라더스","start_time":"19:35","district":"양천구"},{"theater_type":"MEGABOX","theater_name":"목동","city":"서울","movie_title":"슈퍼 마리오 브라더스","start_time":"21:55","district":"양천구"},{"theater_type":"MEGABOX","theater_name":"목동","city":"서울","movie_title":"드림","start_time":"10:40","district":"양천구"},{"theater_type":"MEGABOX","theater_name":"목동","city":"서울","movie_title":"드림","start_time":"13:30","district":"양천구"},{"theater_type":"MEGABOX","theater_name":"목동","city":"서울","movie_title":"드림","start_time":"16:20","district":"양천구"},{"theater_type":"MEGABOX","theater_name":"목동","city":"서울","movie_title":"드림","start_time":"19:10","district":"양천구"},{"theater_type":"MEGABOX","theater_name":"목동","city":"서울","movie_title":"드림","start_time":"22:00","district":"양천구"},{"theater_type":"MEGABOX","theater_name":"목동","city":"서울","movie_title":"드림","start_time":"9:30","district":"양천구"},{"theater_type":"MEGABOX","theater_name":"목동","city":"서울","movie_title":"드림","start_time":"12:20","district":"양천구"},{"theater_type":"MEGABOX","theater_name":"목동","city":"서울","movie_title":"드림","start_time":"15:10","district":"양천구"},{"theater_type":"MEGABOX","theater_name":"목동","city":"서울","movie_title":"드림","start_time":"18:00","district":"양천구"},{"theater_type":"MEGABOX","theater_name":"목동","city":"서울","movie_title":"드림","start_time":"20:50","district":"양천구"},{"theater_type":"MEGABOX","theater_name":"목동","city":"서울","movie_title":"드림","start_time":"11:15","district":"양천구"},{"theater_type":"MEGABOX","theater_name":"목동","city":"서울","movie_title":"드림","start_time":"14:05","district":"양천구"},{"theater_type":"MEGABOX","theater_name":"목동","city":"서울","movie_title":"드림","start_time":"16:55","district":"양천구"},{"theater_type":"MEGABOX","theater_name":"목동","city":"서울","movie_title":"드림","start_time":"19:45","district":"양천구"},{"theater_type":"MEGABOX","theater_name":"목동","city":"서울","movie_title":"드림","start_time":"22:35","district":"양천구"},{"theater_type":"MEGABOX","theater_name":"목동","city":"서울","movie_title":"드림","start_time":"10:05","district":"양천구"},{"theater_type":"MEGABOX","theater_name":"목동","city":"서울","movie_title":"드림","start_time":"12:55","district":"양천구"},{"theater_type":"MEGABOX","theater_name":"목동","city":"서울","movie_title":"드림","start_time":"15:45","district":"양천구"},{"theater_type":"MEGABOX","theater_name":"목동","city":"서울","movie_title":"드림","start_time":"18:35","district":"양천구"},{"theater_type":"MEGABOX","theater_name":"목동","city":"서울","movie_title":"드림","start_time":"21:25","district":"양천구"},{"theater_type":"MEGABOX","theater_name":"목동","city":"서울","movie_title":"더 퍼스트 슬램덩크","start_time":"10:15","district":"양천구"},{"theater_type":"MEGABOX","theater_name":"목동","city":"서울","movie_title":"더 퍼스트 슬램덩크","start_time":"16:00","district":"양천구"},{"theater_type":"MEGABOX","theater_name":"목동","city":"서울","movie_title":"더 퍼스트 슬램덩크","start_time":"18:55","district":"양천구"},{"theater_type":"MEGABOX","theater_name":"목동","city":"서울","movie_title":"스즈메의 문단속","start_time":"13:10","district":"양천구"},{"theater_type":"MEGABOX","theater_name":"목동","city":"서울","movie_title":"스즈메의 문단속","start_time":"21:50","district":"양천구"},{"theater_type":"MEGABOX","theater_name":"목동","city":"서울","movie_title":"스즈메의 문단속","start_time":"14:50","district":"양천구"},{"theater_type":"MEGABOX","theater_name":"목동","city":"서울","movie_title":"스즈메의 문단속","start_time":"20:00","district":"양천구"},{"theater_type":"MEGABOX","theater_name":"목동","city":"서울","movie_title":"존 윅 4","start_time":"9:45","district":"양천구"},{"theater_type":"MEGABOX","theater_name":"목동","city":"서울","movie_title":"존 윅 4","start_time":"13:20","district":"양천구"},{"theater_type":"MEGABOX","theater_name":"목동","city":"서울","movie_title":"존 윅 4","start_time":"16:55","district":"양천구"},{"theater_type":"MEGABOX","theater_name":"목동","city":"서울","movie_title":"존 윅 4","start_time":"20:30","district":"양천구"},{"theater_type":"MEGABOX","theater_name":"목동","city":"서울","movie_title":"리바운드","start_time":"9:45","district":"양천구"},{"theater_type":"MEGABOX","theater_name":"상봉","city":"서울","movie_title":"슈퍼 마리오 브라더스","start_time":"10:10","district":"중랑구"},{"theater_type":"MEGABOX","theater_name":"상봉","city":"서울","movie_title":"슈퍼 마리오 브라더스","start_time":"12:10","district":"중랑구"},{"theater_type":"MEGABOX","theater_name":"상봉","city":"서울","movie_title":"슈퍼 마리오 브라더스","start_time":"14:10","district":"중랑구"},{"theater_type":"MEGABOX","theater_name":"상봉","city":"서울","movie_title":"슈퍼 마리오 브라더스","start_time":"18:10","district":"중랑구"},{"theater_type":"MEGABOX","theater_name":"상봉","city":"서울","movie_title":"슈퍼 마리오 브라더스","start_time":"20:10","district":"중랑구"},{"theater_type":"MEGABOX","theater_name":"상봉","city":"서울","movie_title":"슈퍼 마리오 브라더스","start_time":"16:10","district":"중랑구"},{"theater_type":"MEGABOX","theater_name":"상봉","city":"서울","movie_title":"슈퍼 마리오 브라더스","start_time":"13:10","district":"중랑구"},{"theater_type":"MEGABOX","theater_name":"상봉","city":"서울","movie_title":"슈퍼 마리오 브라더스","start_time":"15:10","district":"중랑구"},{"theater_type":"MEGABOX","theater_name":"상봉","city":"서울","movie_title":"슈퍼 마리오 브라더스","start_time":"17:10","district":"중랑구"},{"theater_type":"MEGABOX","theater_name":"상봉","city":"서울","movie_title":"슈퍼 마리오 브라더스","start_time":"19:10","district":"중랑구"},{"theater_type":"MEGABOX","theater_name":"상봉","city":"서울","movie_title":"슈퍼 마리오 브라더스","start_time":"11:10","district":"중랑구"},{"theater_type":"MEGABOX","theater_name":"상봉","city":"서울","movie_title":"드림","start_time":"9:55","district":"중랑구"},{"theater_type":"MEGABOX","theater_name":"상봉","city":"서울","movie_title":"드림","start_time":"12:25","district":"중랑구"},{"theater_type":"MEGABOX","theater_name":"상봉","city":"서울","movie_title":"드림","start_time":"14:55","district":"중랑구"},{"theater_type":"MEGABOX","theater_name":"상봉","city":"서울","movie_title":"드림","start_time":"17:25","district":"중랑구"},{"theater_type":"MEGABOX","theater_name":"상봉","city":"서울","movie_title":"드림","start_time":"19:55","district":"중랑구"},{"theater_type":"MEGABOX","theater_name":"상봉","city":"서울","movie_title":"드림","start_time":"10:45","district":"중랑구"},{"theater_type":"MEGABOX","theater_name":"상봉","city":"서울","movie_title":"드림","start_time":"13:15","district":"중랑구"},{"theater_type":"MEGABOX","theater_name":"상봉","city":"서울","movie_title":"드림","start_time":"15:45","district":"중랑구"},{"theater_type":"MEGABOX","theater_name":"상봉","city":"서울","movie_title":"드림","start_time":"18:15","district":"중랑구"},{"theater_type":"MEGABOX","theater_name":"상봉","city":"서울","movie_title":"드림","start_time":"20:45","district":"중랑구"},{"theater_type":"MEGABOX","theater_name":"상봉","city":"서울","movie_title":"드림","start_time":"11:30","district":"중랑구"},{"theater_type":"MEGABOX","theater_name":"상봉","city":"서울","movie_title":"드림","start_time":"16:30","district":"중랑구"},{"theater_type":"MEGABOX","theater_name":"상봉","city":"서울","movie_title":"드림","start_time":"19:00","district":"중랑구"},{"theater_type":"MEGABOX","theater_name":"상봉","city":"서울","movie_title":"드림","start_time":"21:30","district":"중랑구"},{"theater_type":"MEGABOX","theater_name":"상봉","city":"서울","movie_title":"더 퍼스트 슬램덩크","start_time":"21:10","district":"중랑구"},{"theater_type":"MEGABOX","theater_name":"상봉","city":"서울","movie_title":"스즈메의 문단속","start_time":"15:00","district":"중랑구"},{"theater_type":"MEGABOX","theater_name":"상봉","city":"서울","movie_title":"존 윅 4","start_time":"17:30","district":"중랑구"},{"theater_type":"MEGABOX","theater_name":"상봉","city":"서울","movie_title":"존 윅 4","start_time":"20:45","district":"중랑구"},{"theater_type":"MEGABOX","theater_name":"상봉","city":"서울","movie_title":"리바운드","start_time":"14:00","district":"중랑구"},{"theater_type":"MEGABOX","theater_name":"상암월드컵경기장","city":"서울","movie_title":"슈퍼 마리오 브라더스","start_time":"10:00","district":"마포구"},{"theater_type":"MEGABOX","theater_name":"상암월드컵경기장","city":"서울","movie_title":"슈퍼 마리오 브라더스","start_time":"12:05","district":"마포구"},{"theater_type":"MEGABOX","theater_name":"상암월드컵경기장","city":"서울","movie_title":"슈퍼 마리오 브라더스","start_time":"14:10","district":"마포구"},{"theater_type":"MEGABOX","theater_name":"상암월드컵경기장","city":"서울","movie_title":"슈퍼 마리오 브라더스","start_time":"18:20","district":"마포구"},{"theater_type":"MEGABOX","theater_name":"상암월드컵경기장","city":"서울","movie_title":"슈퍼 마리오 브라더스","start_time":"20:25","district":"마포구"},{"theater_type":"MEGABOX","theater_name":"상암월드컵경기장","city":"서울","movie_title":"슈퍼 마리오 브라더스","start_time":"16:15","district":"마포구"},{"theater_type":"MEGABOX","theater_name":"상암월드컵경기장","city":"서울","movie_title":"슈퍼 마리오 브라더스","start_time":"8:55","district":"마포구"},{"theater_type":"MEGABOX","theater_name":"상암월드컵경기장","city":"서울","movie_title":"슈퍼 마리오 브라더스","start_time":"11:00","district":"마포구"},{"theater_type":"MEGABOX","theater_name":"상암월드컵경기장","city":"서울","movie_title":"슈퍼 마리오 브라더스","start_time":"13:05","district":"마포구"},{"theater_type":"MEGABOX","theater_name":"상암월드컵경기장","city":"서울","movie_title":"슈퍼 마리오 브라더스","start_time":"15:10","district":"마포구"},{"theater_type":"MEGABOX","theater_name":"상암월드컵경기장","city":"서울","movie_title":"슈퍼 마리오 브라더스","start_time":"17:15","district":"마포구"},{"theater_type":"MEGABOX","theater_name":"상암월드컵경기장","city":"서울","movie_title":"슈퍼 마리오 브라더스","start_time":"19:20","district":"마포구"},{"theater_type":"MEGABOX","theater_name":"상암월드컵경기장","city":"서울","movie_title":"슈퍼 마리오 브라더스","start_time":"21:25","district":"마포구"},{"theater_type":"MEGABOX","theater_name":"상암월드컵경기장","city":"서울","movie_title":"슈퍼 마리오 브라더스","start_time":"23:30","district":"마포구"},{"theater_type":"MEGABOX","theater_name":"상암월드컵경기장","city":"서울","movie_title":"슈퍼 마리오 브라더스","start_time":"10:25","district":"마포구"},{"theater_type":"MEGABOX","theater_name":"상암월드컵경기장","city":"서울","movie_title":"슈퍼 마리오 브라더스","start_time":"12:30","district":"마포구"},{"theater_type":"MEGABOX","theater_name":"상암월드컵경기장","city":"서울","movie_title":"슈퍼 마리오 브라더스","start_time":"14:35","district":"마포구"},{"theater_type":"MEGABOX","theater_name":"상암월드컵경기장","city":"서울","movie_title":"슈퍼 마리오 브라더스","start_time":"16:40","district":"마포구"},{"theater_type":"MEGABOX","theater_name":"상암월드컵경기장","city":"서울","movie_title":"슈퍼 마리오 브라더스","start_time":"18:45","district":"마포구"},{"theater_type":"MEGABOX","theater_name":"상암월드컵경기장","city":"서울","movie_title":"드림","start_time":"10:30","district":"마포구"},{"theater_type":"MEGABOX","theater_name":"상암월드컵경기장","city":"서울","movie_title":"드림","start_time":"13:15","district":"마포구"},{"theater_type":"MEGABOX","theater_name":"상암월드컵경기장","city":"서울","movie_title":"드림","start_time":"15:50","district":"마포구"},{"theater_type":"MEGABOX","theater_name":"상암월드컵경기장","city":"서울","movie_title":"드림","start_time":"18:25","district":"마포구"},{"theater_type":"MEGABOX","theater_name":"상암월드컵경기장","city":"서울","movie_title":"드림","start_time":"21:00","district":"마포구"},{"theater_type":"MEGABOX","theater_name":"상암월드컵경기장","city":"서울","movie_title":"드림","start_time":"23:35","district":"마포구"},{"theater_type":"MEGABOX","theater_name":"상암월드컵경기장","city":"서울","movie_title":"드림","start_time":"9:10","district":"마포구"},{"theater_type":"MEGABOX","theater_name":"상암월드컵경기장","city":"서울","movie_title":"드림","start_time":"11:55","district":"마포구"},{"theater_type":"MEGABOX","theater_name":"상암월드컵경기장","city":"서울","movie_title":"드림","start_time":"14:30","district":"마포구"},{"theater_type":"MEGABOX","theater_name":"상암월드컵경기장","city":"서울","movie_title":"드림","start_time":"17:05","district":"마포구"},{"theater_type":"MEGABOX","theater_name":"상암월드컵경기장","city":"서울","movie_title":"드림","start_time":"19:40","district":"마포구"},{"theater_type":"MEGABOX","theater_name":"상암월드컵경기장","city":"서울","movie_title":"드림","start_time":"22:15","district":"마포구"},{"theater_type":"MEGABOX","theater_name":"상암월드컵경기장","city":"서울","movie_title":"드림","start_time":"12:35","district":"마포구"},{"theater_type":"MEGABOX","theater_name":"상암월드컵경기장","city":"서울","movie_title":"드림","start_time":"15:10","district":"마포구"},{"theater_type":"MEGABOX","theater_name":"상암월드컵경기장","city":"서울","movie_title":"드림","start_time":"17:45","district":"마포구"},{"theater_type":"MEGABOX","theater_name":"상암월드컵경기장","city":"서울","movie_title":"드림","start_time":"20:20","district":"마포구"},{"theater_type":"MEGABOX","theater_name":"상암월드컵경기장","city":"서울","movie_title":"드림","start_time":"22:55","district":"마포구"},{"theater_type":"MEGABOX","theater_name":"상암월드컵경기장","city":"서울","movie_title":"더 퍼스트 슬램덩크","start_time":"20:50","district":"마포구"},{"theater_type":"MEGABOX","theater_name":"상암월드컵경기장","city":"서울","movie_title":"더 퍼스트 슬램덩크","start_time":"23:25","district":"마포구"},{"theater_type":"MEGABOX","theater_name":"상암월드컵경기장","city":"서울","movie_title":"스즈메의 문단속","start_time":"13:25","district":"마포구"},{"theater_type":"MEGABOX","theater_name":"상암월드컵경기장","city":"서울","movie_title":"스즈메의 문단속","start_time":"20:45","district":"마포구"},{"theater_type":"MEGABOX","theater_name":"상암월드컵경기장","city":"서울","movie_title":"스즈메의 문단속","start_time":"23:20","district":"마포구"},{"theater_type":"MEGABOX","theater_name":"상암월드컵경기장","city":"서울","movie_title":"존 윅 4","start_time":"22:30","district":"마포구"},{"theater_type":"MEGABOX","theater_name":"상암월드컵경기장","city":"서울","movie_title":"존 윅 4","start_time":"9:00","district":"마포구"},{"theater_type":"MEGABOX","theater_name":"상암월드컵경기장","city":"서울","movie_title":"존 윅 4","start_time":"12:20","district":"마포구"},{"theater_type":"MEGABOX","theater_name":"상암월드컵경기장","city":"서울","movie_title":"존 윅 4","start_time":"15:45","district":"마포구"},{"theater_type":"MEGABOX","theater_name":"상암월드컵경기장","city":"서울","movie_title":"존 윅 4","start_time":"19:05","district":"마포구"},{"theater_type":"MEGABOX","theater_name":"상암월드컵경기장","city":"서울","movie_title":"리바운드","start_time":"8:50","district":"마포구"},{"theater_type":"MEGABOX","theater_name":"상암월드컵경기장","city":"서울","movie_title":"리바운드","start_time":"18:10","district":"마포구"},{"theater_type":"MEGABOX","theater_name":"성수","city":"서울","movie_title":"슈퍼 마리오 브라더스","start_time":"12:35","district":"성동구"},{"theater_type":"MEGABOX","theater_name":"성수","city":"서울","movie_title":"슈퍼 마리오 브라더스","start_time":"18:35","district":"성동구"},{"theater_type":"MEGABOX","theater_name":"성수","city":"서울","movie_title":"슈퍼 마리오 브라더스","start_time":"14:35","district":"성동구"},{"theater_type":"MEGABOX","theater_name":"성수","city":"서울","movie_title":"슈퍼 마리오 브라더스","start_time":"16:35","district":"성동구"},{"theater_type":"MEGABOX","theater_name":"성수","city":"서울","movie_title":"슈퍼 마리오 브라더스","start_time":"10:55","district":"성동구"},{"theater_type":"MEGABOX","theater_name":"성수","city":"서울","movie_title":"슈퍼 마리오 브라더스","start_time":"15:20","district":"성동구"},{"theater_type":"MEGABOX","theater_name":"성수","city":"서울","movie_title":"슈퍼 마리오 브라더스","start_time":"17:25","district":"성동구"},{"theater_type":"MEGABOX","theater_name":"성수","city":"서울","movie_title":"드림","start_time":"9:50","district":"성동구"},{"theater_type":"MEGABOX","theater_name":"성수","city":"서울","movie_title":"드림","start_time":"12:25","district":"성동구"},{"theater_type":"MEGABOX","theater_name":"성수","city":"서울","movie_title":"드림","start_time":"15:00","district":"성동구"},{"theater_type":"MEGABOX","theater_name":"성수","city":"서울","movie_title":"드림","start_time":"17:35","district":"성동구"},{"theater_type":"MEGABOX","theater_name":"성수","city":"서울","movie_title":"드림","start_time":"20:10","district":"성동구"},{"theater_type":"MEGABOX","theater_name":"성수","city":"서울","movie_title":"드림","start_time":"10:35","district":"성동구"},{"theater_type":"MEGABOX","theater_name":"성수","city":"서울","movie_title":"드림","start_time":"16:00","district":"성동구"},{"theater_type":"MEGABOX","theater_name":"성수","city":"서울","movie_title":"존 윅 4","start_time":"10:00","district":"성동구"},{"theater_type":"MEGABOX","theater_name":"성수","city":"서울","movie_title":"존 윅 4","start_time":"13:20","district":"성동구"},{"theater_type":"MEGABOX","theater_name":"성수","city":"서울","movie_title":"존 윅 4","start_time":"16:40","district":"성동구"},{"theater_type":"MEGABOX","theater_name":"성수","city":"서울","movie_title":"존 윅 4","start_time":"19:55","district":"성동구"},{"theater_type":"MEGABOX","theater_name":"성수","city":"서울","movie_title":"존 윅 4","start_time":"14:20","district":"성동구"},{"theater_type":"MEGABOX","theater_name":"성수","city":"서울","movie_title":"존 윅 4","start_time":"18:30","district":"성동구"},{"theater_type":"MEGABOX","theater_name":"센트럴","city":"서울","movie_title":"슈퍼 마리오 브라더스","start_time":"11:40","district":"서초구"},{"theater_type":"MEGABOX","theater_name":"센트럴","city":"서울","movie_title":"슈퍼 마리오 브라더스","start_time":"9:00","district":"서초구"},{"theater_type":"MEGABOX","theater_name":"센트럴","city":"서울","movie_title":"슈퍼 마리오 브라더스","start_time":"11:00","district":"서초구"},{"theater_type":"MEGABOX","theater_name":"센트럴","city":"서울","movie_title":"슈퍼 마리오 브라더스","start_time":"13:00","district":"서초구"},{"theater_type":"MEGABOX","theater_name":"센트럴","city":"서울","movie_title":"슈퍼 마리오 브라더스","start_time":"15:00","district":"서초구"},{"theater_type":"MEGABOX","theater_name":"센트럴","city":"서울","movie_title":"슈퍼 마리오 브라더스","start_time":"17:00","district":"서초구"},{"theater_type":"MEGABOX","theater_name":"센트럴","city":"서울","movie_title":"슈퍼 마리오 브라더스","start_time":"19:00","district":"서초구"},{"theater_type":"MEGABOX","theater_name":"센트럴","city":"서울","movie_title":"슈퍼 마리오 브라더스","start_time":"21:00","district":"서초구"},{"theater_type":"MEGABOX","theater_name":"센트럴","city":"서울","movie_title":"슈퍼 마리오 브라더스","start_time":"16:00","district":"서초구"},{"theater_type":"MEGABOX","theater_name":"센트럴","city":"서울","movie_title":"드림","start_time":"9:00","district":"서초구"},{"theater_type":"MEGABOX","theater_name":"센트럴","city":"서울","movie_title":"드림","start_time":"11:35","district":"서초구"},{"theater_type":"MEGABOX","theater_name":"센트럴","city":"서울","movie_title":"드림","start_time":"14:10","district":"서초구"},{"theater_type":"MEGABOX","theater_name":"센트럴","city":"서울","movie_title":"드림","start_time":"16:45","district":"서초구"},{"theater_type":"MEGABOX","theater_name":"센트럴","city":"서울","movie_title":"드림","start_time":"19:20","district":"서초구"},{"theater_type":"MEGABOX","theater_name":"센트럴","city":"서울","movie_title":"드림","start_time":"21:55","district":"서초구"},{"theater_type":"MEGABOX","theater_name":"센트럴","city":"서울","movie_title":"드림","start_time":"10:00","district":"서초구"},{"theater_type":"MEGABOX","theater_name":"센트럴","city":"서울","movie_title":"드림","start_time":"12:35","district":"서초구"},{"theater_type":"MEGABOX","theater_name":"센트럴","city":"서울","movie_title":"드림","start_time":"15:10","district":"서초구"},{"theater_type":"MEGABOX","theater_name":"센트럴","city":"서울","movie_title":"드림","start_time":"17:45","district":"서초구"},{"theater_type":"MEGABOX","theater_name":"센트럴","city":"서울","movie_title":"드림","start_time":"20:20","district":"서초구"},{"theater_type":"MEGABOX","theater_name":"센트럴","city":"서울","movie_title":"스즈메의 문단속","start_time":"9:10","district":"서초구"},{"theater_type":"MEGABOX","theater_name":"센트럴","city":"서울","movie_title":"스즈메의 문단속","start_time":"18:00","district":"서초구"},{"theater_type":"MEGABOX","theater_name":"센트럴","city":"서울","movie_title":"존 윅 4","start_time":"16:10","district":"서초구"},{"theater_type":"MEGABOX","theater_name":"센트럴","city":"서울","movie_title":"존 윅 4","start_time":"9:25","district":"서초구"},{"theater_type":"MEGABOX","theater_name":"센트럴","city":"서울","movie_title":"존 윅 4","start_time":"12:45","district":"서초구"},{"theater_type":"MEGABOX","theater_name":"센트럴","city":"서울","movie_title":"존 윅 4","start_time":"20:30","district":"서초구"},{"theater_type":"MEGABOX","theater_name":"센트럴","city":"서울","movie_title":"리바운드","start_time":"13:40","district":"서초구"},{"theater_type":"MEGABOX","theater_name":"송파파크하비오","city":"서울","movie_title":"슈퍼 마리오 브라더스","start_time":"10:00","district":"송파구"},{"theater_type":"MEGABOX","theater_name":"송파파크하비오","city":"서울","movie_title":"슈퍼 마리오 브라더스","start_time":"13:00","district":"송파구"},{"theater_type":"MEGABOX","theater_name":"송파파크하비오","city":"서울","movie_title":"슈퍼 마리오 브라더스","start_time":"15:05","district":"송파구"},{"theater_type":"MEGABOX","theater_name":"송파파크하비오","city":"서울","movie_title":"슈퍼 마리오 브라더스","start_time":"17:10","district":"송파구"},{"theater_type":"MEGABOX","theater_name":"송파파크하비오","city":"서울","movie_title":"슈퍼 마리오 브라더스","start_time":"19:15","district":"송파구"},{"theater_type":"MEGABOX","theater_name":"송파파크하비오","city":"서울","movie_title":"슈퍼 마리오 브라더스","start_time":"9:30","district":"송파구"},{"theater_type":"MEGABOX","theater_name":"송파파크하비오","city":"서울","movie_title":"슈퍼 마리오 브라더스","start_time":"11:35","district":"송파구"},{"theater_type":"MEGABOX","theater_name":"송파파크하비오","city":"서울","movie_title":"슈퍼 마리오 브라더스","start_time":"13:40","district":"송파구"},{"theater_type":"MEGABOX","theater_name":"송파파크하비오","city":"서울","movie_title":"슈퍼 마리오 브라더스","start_time":"15:45","district":"송파구"},{"theater_type":"MEGABOX","theater_name":"송파파크하비오","city":"서울","movie_title":"슈퍼 마리오 브라더스","start_time":"17:50","district":"송파구"},{"theater_type":"MEGABOX","theater_name":"송파파크하비오","city":"서울","movie_title":"슈퍼 마리오 브라더스","start_time":"22:00","district":"송파구"},{"theater_type":"MEGABOX","theater_name":"송파파크하비오","city":"서울","movie_title":"슈퍼 마리오 브라더스","start_time":"19:55","district":"송파구"},{"theater_type":"MEGABOX","theater_name":"송파파크하비오","city":"서울","movie_title":"드림","start_time":"10:00","district":"송파구"},{"theater_type":"MEGABOX","theater_name":"송파파크하비오","city":"서울","movie_title":"드림","start_time":"12:35","district":"송파구"},{"theater_type":"MEGABOX","theater_name":"송파파크하비오","city":"서울","movie_title":"드림","start_time":"15:10","district":"송파구"},{"theater_type":"MEGABOX","theater_name":"송파파크하비오","city":"서울","movie_title":"드림","start_time":"17:45","district":"송파구"},{"theater_type":"MEGABOX","theater_name":"송파파크하비오","city":"서울","movie_title":"드림","start_time":"20:20","district":"송파구"},{"theater_type":"MEGABOX","theater_name":"송파파크하비오","city":"서울","movie_title":"드림","start_time":"10:50","district":"송파구"},{"theater_type":"MEGABOX","theater_name":"송파파크하비오","city":"서울","movie_title":"드림","start_time":"13:25","district":"송파구"},{"theater_type":"MEGABOX","theater_name":"송파파크하비오","city":"서울","movie_title":"드림","start_time":"16:00","district":"송파구"},{"theater_type":"MEGABOX","theater_name":"송파파크하비오","city":"서울","movie_title":"드림","start_time":"18:35","district":"송파구"},{"theater_type":"MEGABOX","theater_name":"송파파크하비오","city":"서울","movie_title":"드림","start_time":"21:10","district":"송파구"},{"theater_type":"MEGABOX","theater_name":"송파파크하비오","city":"서울","movie_title":"드림","start_time":"9:10","district":"송파구"},{"theater_type":"MEGABOX","theater_name":"송파파크하비오","city":"서울","movie_title":"드림","start_time":"11:45","district":"송파구"},{"theater_type":"MEGABOX","theater_name":"송파파크하비오","city":"서울","movie_title":"드림","start_time":"14:20","district":"송파구"},{"theater_type":"MEGABOX","theater_name":"송파파크하비오","city":"서울","movie_title":"드림","start_time":"16:55","district":"송파구"},{"theater_type":"MEGABOX","theater_name":"송파파크하비오","city":"서울","movie_title":"드림","start_time":"19:30","district":"송파구"},{"theater_type":"MEGABOX","theater_name":"송파파크하비오","city":"서울","movie_title":"드림","start_time":"22:05","district":"송파구"},{"theater_type":"MEGABOX","theater_name":"송파파크하비오","city":"서울","movie_title":"더 퍼스트 슬램덩크","start_time":"9:40","district":"송파구"},{"theater_type":"MEGABOX","theater_name":"송파파크하비오","city":"서울","movie_title":"더 퍼스트 슬램덩크","start_time":"18:50","district":"송파구"},{"theater_type":"MEGABOX","theater_name":"송파파크하비오","city":"서울","movie_title":"더 퍼스트 슬램덩크","start_time":"21:25","district":"송파구"},{"theater_type":"MEGABOX","theater_name":"송파파크하비오","city":"서울","movie_title":"더 퍼스트 슬램덩크","start_time":"14:15","district":"송파구"},{"theater_type":"MEGABOX","theater_name":"송파파크하비오","city":"서울","movie_title":"스즈메의 문단속","start_time":"17:00","district":"송파구"},{"theater_type":"MEGABOX","theater_name":"송파파크하비오","city":"서울","movie_title":"스즈메의 문단속","start_time":"19:30","district":"송파구"},{"theater_type":"MEGABOX","theater_name":"송파파크하비오","city":"서울","movie_title":"스즈메의 문단속","start_time":"22:00","district":"송파구"},{"theater_type":"MEGABOX","theater_name":"송파파크하비오","city":"서울","movie_title":"존 윅 4","start_time":"10:50","district":"송파구"},{"theater_type":"MEGABOX","theater_name":"송파파크하비오","city":"서울","movie_title":"존 윅 4","start_time":"14:10","district":"송파구"},{"theater_type":"MEGABOX","theater_name":"송파파크하비오","city":"서울","movie_title":"존 윅 4","start_time":"17:30","district":"송파구"},{"theater_type":"MEGABOX","theater_name":"송파파크하비오","city":"서울","movie_title":"존 윅 4","start_time":"20:50","district":"송파구"},{"theater_type":"MEGABOX","theater_name":"송파파크하비오","city":"서울","movie_title":"존 윅 4","start_time":"9:30","district":"송파구"},{"theater_type":"MEGABOX","theater_name":"송파파크하비오","city":"서울","movie_title":"존 윅 4","start_time":"12:50","district":"송파구"},{"theater_type":"MEGABOX","theater_name":"송파파크하비오","city":"서울","movie_title":"존 윅 4","start_time":"16:10","district":"송파구"},{"theater_type":"MEGABOX","theater_name":"송파파크하비오","city":"서울","movie_title":"존 윅 4","start_time":"19:30","district":"송파구"},{"theater_type":"MEGABOX","theater_name":"송파파크하비오","city":"서울","movie_title":"리바운드","start_time":"12:00","district":"송파구"},{"theater_type":"MEGABOX","theater_name":"신촌","city":"서울","movie_title":"슈퍼 마리오 브라더스","start_time":"9:30","district":"서대문구"},{"theater_type":"MEGABOX","theater_name":"신촌","city":"서울","movie_title":"슈퍼 마리오 브라더스","start_time":"13:30","district":"서대문구"},{"theater_type":"MEGABOX","theater_name":"신촌","city":"서울","movie_title":"슈퍼 마리오 브라더스","start_time":"15:30","district":"서대문구"},{"theater_type":"MEGABOX","theater_name":"신촌","city":"서울","movie_title":"슈퍼 마리오 브라더스","start_time":"17:30","district":"서대문구"},{"theater_type":"MEGABOX","theater_name":"신촌","city":"서울","movie_title":"슈퍼 마리오 브라더스","start_time":"19:30","district":"서대문구"},{"theater_type":"MEGABOX","theater_name":"신촌","city":"서울","movie_title":"슈퍼 마리오 브라더스","start_time":"21:30","district":"서대문구"},{"theater_type":"MEGABOX","theater_name":"신촌","city":"서울","movie_title":"슈퍼 마리오 브라더스","start_time":"11:30","district":"서대문구"},{"theater_type":"MEGABOX","theater_name":"신촌","city":"서울","movie_title":"슈퍼 마리오 브라더스","start_time":"16:40","district":"서대문구"},{"theater_type":"MEGABOX","theater_name":"신촌","city":"서울","movie_title":"슈퍼 마리오 브라더스","start_time":"18:45","district":"서대문구"},{"theater_type":"MEGABOX","theater_name":"신촌","city":"서울","movie_title":"슈퍼 마리오 브라더스","start_time":"20:50","district":"서대문구"},{"theater_type":"MEGABOX","theater_name":"신촌","city":"서울","movie_title":"슈퍼 마리오 브라더스","start_time":"14:35","district":"서대문구"},{"theater_type":"MEGABOX","theater_name":"신촌","city":"서울","movie_title":"드림","start_time":"9:20","district":"서대문구"},{"theater_type":"MEGABOX","theater_name":"신촌","city":"서울","movie_title":"드림","start_time":"11:55","district":"서대문구"},{"theater_type":"MEGABOX","theater_name":"신촌","city":"서울","movie_title":"드림","start_time":"14:30","district":"서대문구"},{"theater_type":"MEGABOX","theater_name":"신촌","city":"서울","movie_title":"드림","start_time":"17:05","district":"서대문구"},{"theater_type":"MEGABOX","theater_name":"신촌","city":"서울","movie_title":"드림","start_time":"19:40","district":"서대문구"},{"theater_type":"MEGABOX","theater_name":"신촌","city":"서울","movie_title":"드림","start_time":"22:15","district":"서대문구"},{"theater_type":"MEGABOX","theater_name":"신촌","city":"서울","movie_title":"드림","start_time":"10:10","district":"서대문구"},{"theater_type":"MEGABOX","theater_name":"신촌","city":"서울","movie_title":"드림","start_time":"12:45","district":"서대문구"},{"theater_type":"MEGABOX","theater_name":"신촌","city":"서울","movie_title":"드림","start_time":"15:20","district":"서대문구"},{"theater_type":"MEGABOX","theater_name":"신촌","city":"서울","movie_title":"드림","start_time":"11:10","district":"서대문구"},{"theater_type":"MEGABOX","theater_name":"신촌","city":"서울","movie_title":"드림","start_time":"13:45","district":"서대문구"},{"theater_type":"MEGABOX","theater_name":"신촌","city":"서울","movie_title":"드림","start_time":"16:20","district":"서대문구"},{"theater_type":"MEGABOX","theater_name":"신촌","city":"서울","movie_title":"드림","start_time":"19:00","district":"서대문구"},{"theater_type":"MEGABOX","theater_name":"신촌","city":"서울","movie_title":"드림","start_time":"21:35","district":"서대문구"},{"theater_type":"MEGABOX","theater_name":"신촌","city":"서울","movie_title":"더 퍼스트 슬램덩크","start_time":"9:25","district":"서대문구"},{"theater_type":"MEGABOX","theater_name":"신촌","city":"서울","movie_title":"더 퍼스트 슬램덩크","start_time":"12:00","district":"서대문구"},{"theater_type":"MEGABOX","theater_name":"신촌","city":"서울","movie_title":"더 퍼스트 슬램덩크","start_time":"22:20","district":"서대문구"},{"theater_type":"MEGABOX","theater_name":"신촌","city":"서울","movie_title":"더 퍼스트 슬램덩크","start_time":"14:40","district":"서대문구"},{"theater_type":"MEGABOX","theater_name":"신촌","city":"서울","movie_title":"더 퍼스트 슬램덩크","start_time":"20:10","district":"서대문구"},{"theater_type":"MEGABOX","theater_name":"신촌","city":"서울","movie_title":"스즈메의 문단속","start_time":"21:20","district":"서대문구"},{"theater_type":"MEGABOX","theater_name":"신촌","city":"서울","movie_title":"스즈메의 문단속","start_time":"12:00","district":"서대문구"},{"theater_type":"MEGABOX","theater_name":"신촌","city":"서울","movie_title":"스즈메의 문단속","start_time":"15:00","district":"서대문구"},{"theater_type":"MEGABOX","theater_name":"신촌","city":"서울","movie_title":"스즈메의 문단속","start_time":"17:35","district":"서대문구"},{"theater_type":"MEGABOX","theater_name":"신촌","city":"서울","movie_title":"존 윅 4","start_time":"18:00","district":"서대문구"},{"theater_type":"MEGABOX","theater_name":"신촌","city":"서울","movie_title":"존 윅 4","start_time":"10:20","district":"서대문구"},{"theater_type":"MEGABOX","theater_name":"신촌","city":"서울","movie_title":"존 윅 4","start_time":"16:45","district":"서대문구"},{"theater_type":"MEGABOX","theater_name":"신촌","city":"서울","movie_title":"존 윅 4","start_time":"20:05","district":"서대문구"},{"theater_type":"MEGABOX","theater_name":"이수","city":"서울","movie_title":"슈퍼 마리오 브라더스","start_time":"9:40","district":"동작구"},{"theater_type":"MEGABOX","theater_name":"이수","city":"서울","movie_title":"슈퍼 마리오 브라더스","start_time":"11:40","district":"동작구"},{"theater_type":"MEGABOX","theater_name":"이수","city":"서울","movie_title":"슈퍼 마리오 브라더스","start_time":"17:40","district":"동작구"},{"theater_type":"MEGABOX","theater_name":"이수","city":"서울","movie_title":"슈퍼 마리오 브라더스","start_time":"19:40","district":"동작구"},{"theater_type":"MEGABOX","theater_name":"이수","city":"서울","movie_title":"슈퍼 마리오 브라더스","start_time":"21:40","district":"동작구"},{"theater_type":"MEGABOX","theater_name":"이수","city":"서울","movie_title":"슈퍼 마리오 브라더스","start_time":"13:40","district":"동작구"},{"theater_type":"MEGABOX","theater_name":"이수","city":"서울","movie_title":"슈퍼 마리오 브라더스","start_time":"15:40","district":"동작구"},{"theater_type":"MEGABOX","theater_name":"이수","city":"서울","movie_title":"슈퍼 마리오 브라더스","start_time":"12:40","district":"동작구"},{"theater_type":"MEGABOX","theater_name":"이수","city":"서울","movie_title":"슈퍼 마리오 브라더스","start_time":"14:40","district":"동작구"},{"theater_type":"MEGABOX","theater_name":"이수","city":"서울","movie_title":"슈퍼 마리오 브라더스","start_time":"16:50","district":"동작구"},{"theater_type":"MEGABOX","theater_name":"이수","city":"서울","movie_title":"드림","start_time":"9:20","district":"동작구"},{"theater_type":"MEGABOX","theater_name":"이수","city":"서울","movie_title":"드림","start_time":"11:55","district":"동작구"},{"theater_type":"MEGABOX","theater_name":"이수","city":"서울","movie_title":"드림","start_time":"14:30","district":"동작구"},{"theater_type":"MEGABOX","theater_name":"이수","city":"서울","movie_title":"드림","start_time":"17:05","district":"동작구"},{"theater_type":"MEGABOX","theater_name":"이수","city":"서울","movie_title":"드림","start_time":"19:40","district":"동작구"},{"theater_type":"MEGABOX","theater_name":"이수","city":"서울","movie_title":"드림","start_time":"10:40","district":"동작구"},{"theater_type":"MEGABOX","theater_name":"이수","city":"서울","movie_title":"드림","start_time":"13:15","district":"동작구"},{"theater_type":"MEGABOX","theater_name":"이수","city":"서울","movie_title":"드림","start_time":"15:50","district":"동작구"},{"theater_type":"MEGABOX","theater_name":"이수","city":"서울","movie_title":"드림","start_time":"18:25","district":"동작구"},{"theater_type":"MEGABOX","theater_name":"이수","city":"서울","movie_title":"드림","start_time":"21:00","district":"동작구"},{"theater_type":"MEGABOX","theater_name":"이수","city":"서울","movie_title":"스즈메의 문단속","start_time":"10:00","district":"동작구"},{"theater_type":"MEGABOX","theater_name":"이수","city":"서울","movie_title":"스즈메의 문단속","start_time":"19:00","district":"동작구"},{"theater_type":"MEGABOX","theater_name":"이수","city":"서울","movie_title":"스즈메의 문단속","start_time":"21:30","district":"동작구"},{"theater_type":"MEGABOX","theater_name":"이수","city":"서울","movie_title":"존 윅 4","start_time":"10:00","district":"동작구"},{"theater_type":"MEGABOX","theater_name":"이수","city":"서울","movie_title":"존 윅 4","start_time":"13:20","district":"동작구"},{"theater_type":"MEGABOX","theater_name":"이수","city":"서울","movie_title":"존 윅 4","start_time":"16:40","district":"동작구"},{"theater_type":"MEGABOX","theater_name":"이수","city":"서울","movie_title":"존 윅 4","start_time":"20:00","district":"동작구"},{"theater_type":"MEGABOX","theater_name":"이수","city":"서울","movie_title":"리바운드","start_time":"11:35","district":"동작구"},{"theater_type":"MEGABOX","theater_name":"이수","city":"서울","movie_title":"리바운드","start_time":"19:00","district":"동작구"},{"theater_type":"MEGABOX","theater_name":"창동","city":"서울","movie_title":"슈퍼 마리오 브라더스","start_time":"10:05","district":"도봉구"},{"theater_type":"MEGABOX","theater_name":"창동","city":"서울","movie_title":"슈퍼 마리오 브라더스","start_time":"12:20","district":"도봉구"},{"theater_type":"MEGABOX","theater_name":"창동","city":"서울","movie_title":"슈퍼 마리오 브라더스","start_time":"14:30","district":"도봉구"},{"theater_type":"MEGABOX","theater_name":"창동","city":"서울","movie_title":"슈퍼 마리오 브라더스","start_time":"16:40","district":"도봉구"},{"theater_type":"MEGABOX","theater_name":"창동","city":"서울","movie_title":"슈퍼 마리오 브라더스","start_time":"18:50","district":"도봉구"},{"theater_type":"MEGABOX","theater_name":"창동","city":"서울","movie_title":"슈퍼 마리오 브라더스","start_time":"21:00","district":"도봉구"},{"theater_type":"MEGABOX","theater_name":"창동","city":"서울","movie_title":"슈퍼 마리오 브라더스","start_time":"9:30","district":"도봉구"},{"theater_type":"MEGABOX","theater_name":"창동","city":"서울","movie_title":"슈퍼 마리오 브라더스","start_time":"11:35","district":"도봉구"},{"theater_type":"MEGABOX","theater_name":"창동","city":"서울","movie_title":"슈퍼 마리오 브라더스","start_time":"13:40","district":"도봉구"},{"theater_type":"MEGABOX","theater_name":"창동","city":"서울","movie_title":"슈퍼 마리오 브라더스","start_time":"15:45","district":"도봉구"},{"theater_type":"MEGABOX","theater_name":"창동","city":"서울","movie_title":"드림","start_time":"9:35","district":"도봉구"},{"theater_type":"MEGABOX","theater_name":"창동","city":"서울","movie_title":"드림","start_time":"12:15","district":"도봉구"},{"theater_type":"MEGABOX","theater_name":"창동","city":"서울","movie_title":"드림","start_time":"14:55","district":"도봉구"},{"theater_type":"MEGABOX","theater_name":"창동","city":"서울","movie_title":"드림","start_time":"17:35","district":"도봉구"},{"theater_type":"MEGABOX","theater_name":"창동","city":"서울","movie_title":"드림","start_time":"20:15","district":"도봉구"},{"theater_type":"MEGABOX","theater_name":"창동","city":"서울","movie_title":"드림","start_time":"10:15","district":"도봉구"},{"theater_type":"MEGABOX","theater_name":"창동","city":"서울","movie_title":"드림","start_time":"12:55","district":"도봉구"},{"theater_type":"MEGABOX","theater_name":"창동","city":"서울","movie_title":"드림","start_time":"15:35","district":"도봉구"},{"theater_type":"MEGABOX","theater_name":"창동","city":"서울","movie_title":"드림","start_time":"18:15","district":"도봉구"},{"theater_type":"MEGABOX","theater_name":"창동","city":"서울","movie_title":"드림","start_time":"20:55","district":"도봉구"},{"theater_type":"MEGABOX","theater_name":"창동","city":"서울","movie_title":"스즈메의 문단속","start_time":"17:50","district":"도봉구"},{"theater_type":"MEGABOX","theater_name":"창동","city":"서울","movie_title":"스즈메의 문단속","start_time":"9:30","district":"도봉구"},{"theater_type":"MEGABOX","theater_name":"창동","city":"서울","movie_title":"스즈메의 문단속","start_time":"14:40","district":"도봉구"},{"theater_type":"MEGABOX","theater_name":"창동","city":"서울","movie_title":"존 윅 4","start_time":"20:25","district":"도봉구"},{"theater_type":"MEGABOX","theater_name":"창동","city":"서울","movie_title":"존 윅 4","start_time":"17:15","district":"도봉구"},{"theater_type":"MEGABOX","theater_name":"창동","city":"서울","movie_title":"리바운드","start_time":"12:05","district":"도봉구"},{"theater_type":"MEGABOX","theater_name":"창동","city":"서울","movie_title":"리바운드","start_time":"20:40","district":"도봉구"},{"theater_type":"MEGABOX","theater_name":"코엑스","city":"서울","movie_title":"슈퍼 마리오 브라더스","start_time":"9:10","district":"강남구"},{"theater_type":"MEGABOX","theater_name":"코엑스","city":"서울","movie_title":"슈퍼 마리오 브라더스","start_time":"11:20","district":"강남구"},{"theater_type":"MEGABOX","theater_name":"코엑스","city":"서울","movie_title":"슈퍼 마리오 브라더스","start_time":"15:50","district":"강남구"},{"theater_type":"MEGABOX","theater_name":"코엑스","city":"서울","movie_title":"슈퍼 마리오 브라더스","start_time":"18:00","district":"강남구"},{"theater_type":"MEGABOX","theater_name":"코엑스","city":"서울","movie_title":"슈퍼 마리오 브라더스","start_time":"20:10","district":"강남구"},{"theater_type":"MEGABOX","theater_name":"코엑스","city":"서울","movie_title":"슈퍼 마리오 브라더스","start_time":"13:35","district":"강남구"},{"theater_type":"MEGABOX","theater_name":"코엑스","city":"서울","movie_title":"슈퍼 마리오 브라더스","start_time":"8:35","district":"강남구"},{"theater_type":"MEGABOX","theater_name":"코엑스","city":"서울","movie_title":"슈퍼 마리오 브라더스","start_time":"10:40","district":"강남구"},{"theater_type":"MEGABOX","theater_name":"코엑스","city":"서울","movie_title":"슈퍼 마리오 브라더스","start_time":"12:45","district":"강남구"},{"theater_type":"MEGABOX","theater_name":"코엑스","city":"서울","movie_title":"슈퍼 마리오 브라더스","start_time":"14:50","district":"강남구"},{"theater_type":"MEGABOX","theater_name":"코엑스","city":"서울","movie_title":"슈퍼 마리오 브라더스","start_time":"16:55","district":"강남구"},{"theater_type":"MEGABOX","theater_name":"코엑스","city":"서울","movie_title":"슈퍼 마리오 브라더스","start_time":"19:00","district":"강남구"},{"theater_type":"MEGABOX","theater_name":"코엑스","city":"서울","movie_title":"슈퍼 마리오 브라더스","start_time":"21:05","district":"강남구"},{"theater_type":"MEGABOX","theater_name":"코엑스","city":"서울","movie_title":"슈퍼 마리오 브라더스","start_time":"23:10","district":"강남구"},{"theater_type":"MEGABOX","theater_name":"코엑스","city":"서울","movie_title":"슈퍼 마리오 브라더스","start_time":"20:00","district":"강남구"},{"theater_type":"MEGABOX","theater_name":"코엑스","city":"서울","movie_title":"슈퍼 마리오 브라더스","start_time":"9:50","district":"강남구"},{"theater_type":"MEGABOX","theater_name":"코엑스","city":"서울","movie_title":"슈퍼 마리오 브라더스","start_time":"11:55","district":"강남구"},{"theater_type":"MEGABOX","theater_name":"코엑스","city":"서울","movie_title":"슈퍼 마리오 브라더스","start_time":"14:00","district":"강남구"},{"theater_type":"MEGABOX","theater_name":"코엑스","city":"서울","movie_title":"슈퍼 마리오 브라더스","start_time":"17:35","district":"강남구"},{"theater_type":"MEGABOX","theater_name":"코엑스","city":"서울","movie_title":"슈퍼 마리오 브라더스","start_time":"19:40","district":"강남구"},{"theater_type":"MEGABOX","theater_name":"코엑스","city":"서울","movie_title":"슈퍼 마리오 브라더스","start_time":"21:45","district":"강남구"},{"theater_type":"MEGABOX","theater_name":"코엑스","city":"서울","movie_title":"슈퍼 마리오 브라더스","start_time":"15:25","district":"강남구"},{"theater_type":"MEGABOX","theater_name":"코엑스","city":"서울","movie_title":"슈퍼 마리오 브라더스","start_time":"9:00","district":"강남구"},{"theater_type":"MEGABOX","theater_name":"코엑스","city":"서울","movie_title":"슈퍼 마리오 브라더스","start_time":"11:15","district":"강남구"},{"theater_type":"MEGABOX","theater_name":"코엑스","city":"서울","movie_title":"슈퍼 마리오 브라더스","start_time":"13:30","district":"강남구"},{"theater_type":"MEGABOX","theater_name":"코엑스","city":"서울","movie_title":"슈퍼 마리오 브라더스","start_time":"15:45","district":"강남구"},{"theater_type":"MEGABOX","theater_name":"코엑스","city":"서울","movie_title":"슈퍼 마리오 브라더스","start_time":"13:00","district":"강남구"},{"theater_type":"MEGABOX","theater_name":"코엑스","city":"서울","movie_title":"슈퍼 마리오 브라더스","start_time":"22:15","district":"강남구"},{"theater_type":"MEGABOX","theater_name":"코엑스","city":"서울","movie_title":"드림","start_time":"9:00","district":"강남구"},{"theater_type":"MEGABOX","theater_name":"코엑스","city":"서울","movie_title":"드림","start_time":"11:35","district":"강남구"},{"theater_type":"MEGABOX","theater_name":"코엑스","city":"서울","movie_title":"드림","start_time":"14:10","district":"강남구"},{"theater_type":"MEGABOX","theater_name":"코엑스","city":"서울","movie_title":"드림","start_time":"16:45","district":"강남구"},{"theater_type":"MEGABOX","theater_name":"코엑스","city":"서울","movie_title":"드림","start_time":"22:00","district":"강남구"},{"theater_type":"MEGABOX","theater_name":"코엑스","city":"서울","movie_title":"드림","start_time":"8:30","district":"강남구"},{"theater_type":"MEGABOX","theater_name":"코엑스","city":"서울","movie_title":"드림","start_time":"11:05","district":"강남구"},{"theater_type":"MEGABOX","theater_name":"코엑스","city":"서울","movie_title":"드림","start_time":"13:40","district":"강남구"},{"theater_type":"MEGABOX","theater_name":"코엑스","city":"서울","movie_title":"드림","start_time":"16:20","district":"강남구"},{"theater_type":"MEGABOX","theater_name":"코엑스","city":"서울","movie_title":"드림","start_time":"19:00","district":"강남구"},{"theater_type":"MEGABOX","theater_name":"코엑스","city":"서울","movie_title":"드림","start_time":"21:35","district":"강남구"},{"theater_type":"MEGABOX","theater_name":"코엑스","city":"서울","movie_title":"드림","start_time":"10:20","district":"강남구"},{"theater_type":"MEGABOX","theater_name":"코엑스","city":"서울","movie_title":"드림","start_time":"12:55","district":"강남구"},{"theater_type":"MEGABOX","theater_name":"코엑스","city":"서울","movie_title":"드림","start_time":"15:30","district":"강남구"},{"theater_type":"MEGABOX","theater_name":"코엑스","city":"서울","movie_title":"드림","start_time":"18:10","district":"강남구"},{"theater_type":"MEGABOX","theater_name":"코엑스","city":"서울","movie_title":"드림","start_time":"20:45","district":"강남구"},{"theater_type":"MEGABOX","theater_name":"코엑스","city":"서울","movie_title":"드림","start_time":"23:20","district":"강남구"},{"theater_type":"MEGABOX","theater_name":"코엑스","city":"서울","movie_title":"드림","start_time":"9:40","district":"강남구"},{"theater_type":"MEGABOX","theater_name":"코엑스","city":"서울","movie_title":"드림","start_time":"12:15","district":"강남구"},{"theater_type":"MEGABOX","theater_name":"코엑스","city":"서울","movie_title":"드림","start_time":"14:50","district":"강남구"},{"theater_type":"MEGABOX","theater_name":"코엑스","city":"서울","movie_title":"드림","start_time":"17:25","district":"강남구"},{"theater_type":"MEGABOX","theater_name":"코엑스","city":"서울","movie_title":"드림","start_time":"20:00","district":"강남구"},{"theater_type":"MEGABOX","theater_name":"코엑스","city":"서울","movie_title":"드림","start_time":"22:35","district":"강남구"},{"theater_type":"MEGABOX","theater_name":"코엑스","city":"서울","movie_title":"드림","start_time":"9:10","district":"강남구"},{"theater_type":"MEGABOX","theater_name":"코엑스","city":"서울","movie_title":"드림","start_time":"11:55","district":"강남구"},{"theater_type":"MEGABOX","theater_name":"코엑스","city":"서울","movie_title":"드림","start_time":"14:40","district":"강남구"},{"theater_type":"MEGABOX","theater_name":"코엑스","city":"서울","movie_title":"드림","start_time":"20:15","district":"강남구"},{"theater_type":"MEGABOX","theater_name":"코엑스","city":"서울","movie_title":"드림","start_time":"23:00","district":"강남구"},{"theater_type":"MEGABOX","theater_name":"코엑스","city":"서울","movie_title":"더 퍼스트 슬램덩크","start_time":"22:25","district":"강남구"},{"theater_type":"MEGABOX","theater_name":"코엑스","city":"서울","movie_title":"더 퍼스트 슬램덩크","start_time":"17:10","district":"강남구"},{"theater_type":"MEGABOX","theater_name":"코엑스","city":"서울","movie_title":"더 퍼스트 슬램덩크","start_time":"22:20","district":"강남구"},{"theater_type":"MEGABOX","theater_name":"코엑스","city":"서울","movie_title":"더 퍼스트 슬램덩크","start_time":"11:55","district":"강남구"},{"theater_type":"MEGABOX","theater_name":"코엑스","city":"서울","movie_title":"스즈메의 문단속","start_time":"9:20","district":"강남구"},{"theater_type":"MEGABOX","theater_name":"코엑스","city":"서울","movie_title":"스즈메의 문단속","start_time":"14:30","district":"강남구"},{"theater_type":"MEGABOX","theater_name":"코엑스","city":"서울","movie_title":"스즈메의 문단속","start_time":"19:45","district":"강남구"},{"theater_type":"MEGABOX","theater_name":"코엑스","city":"서울","movie_title":"존 윅 4","start_time":"10:00","district":"강남구"},{"theater_type":"MEGABOX","theater_name":"코엑스","city":"서울","movie_title":"존 윅 4","start_time":"13:20","district":"강남구"},{"theater_type":"MEGABOX","theater_name":"코엑스","city":"서울","movie_title":"존 윅 4","start_time":"16:40","district":"강남구"},{"theater_type":"MEGABOX","theater_name":"코엑스","city":"서울","movie_title":"존 윅 4","start_time":"22:10","district":"강남구"},{"theater_type":"MEGABOX","theater_name":"코엑스","city":"서울","movie_title":"존 윅 4","start_time":"16:05","district":"강남구"},{"theater_type":"MEGABOX","theater_name":"코엑스","city":"서울","movie_title":"존 윅 4","start_time":"19:25","district":"강남구"},{"theater_type":"MEGABOX","theater_name":"코엑스","city":"서울","movie_title":"존 윅 4","start_time":"22:45","district":"강남구"},{"theater_type":"MEGABOX","theater_name":"코엑스","city":"서울","movie_title":"존 윅 4","start_time":"8:45","district":"강남구"},{"theater_type":"MEGABOX","theater_name":"코엑스","city":"서울","movie_title":"존 윅 4","start_time":"12:05","district":"강남구"},{"theater_type":"MEGABOX","theater_name":"코엑스","city":"서울","movie_title":"존 윅 4","start_time":"18:00","district":"강남구"},{"theater_type":"MEGABOX","theater_name":"코엑스","city":"서울","movie_title":"존 윅 4","start_time":"21:30","district":"강남구"},{"theater_type":"MEGABOX","theater_name":"코엑스","city":"서울","movie_title":"존 윅 4","start_time":"9:30","district":"강남구"},{"theater_type":"MEGABOX","theater_name":"코엑스","city":"서울","movie_title":"존 윅 4","start_time":"15:15","district":"강남구"},{"theater_type":"MEGABOX","theater_name":"코엑스","city":"서울","movie_title":"존 윅 4","start_time":"18:45","district":"강남구"},{"theater_type":"MEGABOX","theater_name":"코엑스","city":"서울","movie_title":"리바운드","start_time":"12:35","district":"강남구"},{"theater_type":"MEGABOX","theater_name":"코엑스","city":"서울","movie_title":"리바운드","start_time":"17:55","district":"강남구"},{"theater_type":"MEGABOX","theater_name":"홍대","city":"서울","movie_title":"슈퍼 마리오 브라더스","start_time":"10:30","district":"마포구"},{"theater_type":"MEGABOX","theater_name":"홍대","city":"서울","movie_title":"슈퍼 마리오 브라더스","start_time":"12:30","district":"마포구"},{"theater_type":"MEGABOX","theater_name":"홍대","city":"서울","movie_title":"슈퍼 마리오 브라더스","start_time":"14:30","district":"마포구"},{"theater_type":"MEGABOX","theater_name":"홍대","city":"서울","movie_title":"슈퍼 마리오 브라더스","start_time":"16:30","district":"마포구"},{"theater_type":"MEGABOX","theater_name":"홍대","city":"서울","movie_title":"슈퍼 마리오 브라더스","start_time":"18:30","district":"마포구"},{"theater_type":"MEGABOX","theater_name":"홍대","city":"서울","movie_title":"슈퍼 마리오 브라더스","start_time":"20:30","district":"마포구"},{"theater_type":"MEGABOX","theater_name":"홍대","city":"서울","movie_title":"슈퍼 마리오 브라더스","start_time":"22:30","district":"마포구"},{"theater_type":"MEGABOX","theater_name":"홍대","city":"서울","movie_title":"드림","start_time":"11:45","district":"마포구"},{"theater_type":"MEGABOX","theater_name":"홍대","city":"서울","movie_title":"드림","start_time":"14:20","district":"마포구"},{"theater_type":"MEGABOX","theater_name":"홍대","city":"서울","movie_title":"드림","start_time":"16:55","district":"마포구"},{"theater_type":"MEGABOX","theater_name":"홍대","city":"서울","movie_title":"드림","start_time":"19:30","district":"마포구"},{"theater_type":"MEGABOX","theater_name":"홍대","city":"서울","movie_title":"드림","start_time":"22:05","district":"마포구"},{"theater_type":"MEGABOX","theater_name":"홍대","city":"서울","movie_title":"드림","start_time":"10:30","district":"마포구"},{"theater_type":"MEGABOX","theater_name":"홍대","city":"서울","movie_title":"드림","start_time":"13:05","district":"마포구"},{"theater_type":"MEGABOX","theater_name":"홍대","city":"서울","movie_title":"드림","start_time":"15:40","district":"마포구"},{"theater_type":"MEGABOX","theater_name":"홍대","city":"서울","movie_title":"드림","start_time":"18:15","district":"마포구"},{"theater_type":"MEGABOX","theater_name":"홍대","city":"서울","movie_title":"드림","start_time":"20:50","district":"마포구"},{"theater_type":"MEGABOX","theater_name":"홍대","city":"서울","movie_title":"더 퍼스트 슬램덩크","start_time":"17:05","district":"마포구"},{"theater_type":"MEGABOX","theater_name":"홍대","city":"서울","movie_title":"스즈메의 문단속","start_time":"11:15","district":"마포구"},{"theater_type":"MEGABOX","theater_name":"홍대","city":"서울","movie_title":"스즈메의 문단속","start_time":"16:25","district":"마포구"},{"theater_type":"MEGABOX","theater_name":"홍대","city":"서울","movie_title":"스즈메의 문단속","start_time":"22:15","district":"마포구"},{"theater_type":"MEGABOX","theater_name":"홍대","city":"서울","movie_title":"리바운드","start_time":"18:55","district":"마포구"},{"theater_type":"MEGABOX","theater_name":"화곡","city":"서울","movie_title":"슈퍼 마리오 브라더스","start_time":"9:50","district":"강서구"},{"theater_type":"MEGABOX","theater_name":"화곡","city":"서울","movie_title":"슈퍼 마리오 브라더스","start_time":"11:50","district":"강서구"},{"theater_type":"MEGABOX","theater_name":"화곡","city":"서울","movie_title":"슈퍼 마리오 브라더스","start_time":"13:50","district":"강서구"},{"theater_type":"MEGABOX","theater_name":"화곡","city":"서울","movie_title":"슈퍼 마리오 브라더스","start_time":"15:50","district":"강서구"},{"theater_type":"MEGABOX","theater_name":"화곡","city":"서울","movie_title":"슈퍼 마리오 브라더스","start_time":"17:50","district":"강서구"},{"theater_type":"MEGABOX","theater_name":"화곡","city":"서울","movie_title":"슈퍼 마리오 브라더스","start_time":"19:50","district":"강서구"},{"theater_type":"MEGABOX","theater_name":"화곡","city":"서울","movie_title":"슈퍼 마리오 브라더스","start_time":"21:50","district":"강서구"},{"theater_type":"MEGABOX","theater_name":"화곡","city":"서울","movie_title":"슈퍼 마리오 브라더스","start_time":"10:50","district":"강서구"},{"theater_type":"MEGABOX","theater_name":"화곡","city":"서울","movie_title":"슈퍼 마리오 브라더스","start_time":"12:55","district":"강서구"},{"theater_type":"MEGABOX","theater_name":"화곡","city":"서울","movie_title":"드림","start_time":"11:00","district":"강서구"},{"theater_type":"MEGABOX","theater_name":"화곡","city":"서울","movie_title":"드림","start_time":"13:35","district":"강서구"},{"theater_type":"MEGABOX","theater_name":"화곡","city":"서울","movie_title":"드림","start_time":"16:10","district":"강서구"},{"theater_type":"MEGABOX","theater_name":"화곡","city":"서울","movie_title":"드림","start_time":"18:45","district":"강서구"},{"theater_type":"MEGABOX","theater_name":"화곡","city":"서울","movie_title":"드림","start_time":"21:20","district":"강서구"},{"theater_type":"MEGABOX","theater_name":"화곡","city":"서울","movie_title":"드림","start_time":"10:00","district":"강서구"},{"theater_type":"MEGABOX","theater_name":"화곡","city":"서울","movie_title":"드림","start_time":"12:35","district":"강서구"},{"theater_type":"MEGABOX","theater_name":"화곡","city":"서울","movie_title":"드림","start_time":"15:10","district":"강서구"},{"theater_type":"MEGABOX","theater_name":"화곡","city":"서울","movie_title":"드림","start_time":"17:45","district":"강서구"},{"theater_type":"MEGABOX","theater_name":"화곡","city":"서울","movie_title":"드림","start_time":"20:20","district":"강서구"},{"theater_type":"MEGABOX","theater_name":"화곡","city":"서울","movie_title":"스즈메의 문단속","start_time":"13:55","district":"강서구"},{"theater_type":"MEGABOX","theater_name":"화곡","city":"서울","movie_title":"존 윅 4","start_time":"17:35","district":"강서구"},{"theater_type":"MEGABOX","theater_name":"화곡","city":"서울","movie_title":"존 윅 4","start_time":"20:55","district":"강서구"},{"theater_type":"MEGABOX","theater_name":"화곡","city":"서울","movie_title":"존 윅 4","start_time":"10:35","district":"강서구"},{"theater_type":"MEGABOX","theater_name":"화곡","city":"서울","movie_title":"존 윅 4","start_time":"16:25","district":"강서구"},{"theater_type":"MEGABOX","theater_name":"화곡","city":"서울","movie_title":"존 윅 4","start_time":"19:45","district":"강서구"},{"theater_type":"MEGABOX","theater_name":"화곡","city":"서울","movie_title":"리바운드","start_time":"15:00","district":"강서구"},{"theater_type":"MEGABOX","theater_name":"광명AK프라자","city":"경기","movie_title":"슈퍼 마리오 브라더스","start_time":"20:10","district":"광명시"},{"theater_type":"MEGABOX","theater_name":"광명AK프라자","city":"경기","movie_title":"슈퍼 마리오 브라더스","start_time":"15:35","district":"광명시"},{"theater_type":"MEGABOX","theater_name":"광명AK프라자","city":"경기","movie_title":"슈퍼 마리오 브라더스","start_time":"16:35","district":"광명시"},{"theater_type":"MEGABOX","theater_name":"광명AK프라자","city":"경기","movie_title":"슈퍼 마리오 브라더스","start_time":"18:00","district":"광명시"},{"theater_type":"MEGABOX","theater_name":"영종","city":"인천","movie_title":"슈퍼 마리오 브라더스","start_time":"17:00","district":"중구"},{"theater_type":"MEGABOX","theater_name":"영종","city":"인천","movie_title":"슈퍼 마리오 브라더스","start_time":"19:00","district":"중구"},{"theater_type":"MEGABOX","theater_name":"영종","city":"인천","movie_title":"슈퍼 마리오 브라더스","start_time":"21:00","district":"중구"},{"theater_type":"MEGABOX","theater_name":"영종","city":"인천","movie_title":"슈퍼 마리오 브라더스","start_time":"15:00","district":"중구"}]